{
  "id": "ExgiWjguQxj10SYTtS1GP",
  "name": "ILCCD_GO_TO_TOP_UP",
  "projectId": "652fcbce09869c3c809b3097",
  "gitBranchName": "master",
  "services": [
    {
      "type": "1",
      "command": {
        "type": "3",
        "attributes": {
          "nextWidgetId": "-8htlEh04-3YsEy74xFy7",
          "gridRadioValue": "",
          "selectedObjectBindingKey": "selectedObject",
          "editableForm": false
        }
      }
    }
  ],
  "csrf": "0.6bnoccaxkikPzRi5YYKNK6Mxi-PnnE-i",
  "_id": "qVbQ6YYvyIUPUZL3dPzcv",
  "updatedAt": "3/3/2024",
  "createdAt": "3/3/2024",
  "createdBy": "talha",
  "updatedBy": "talha"
}
