{
  "id": "gUSWdqEWjbV87POEsLfwx",
  "gitBranchName": "master",
  "name": "ILCG_IMAGE_UPLOAD",
  "projectId": "652fcbce09869c3c809b3097",
  "services": [
    {
      "type": "16",
      "command": {
        "type": "1",
        "attributes": {
          "bindingKey": "IMAGE_UPLOAD",
          "storeType": 1,
          "fileType": "img",
          "maxSize": "1000",
          "uploadTrigger": {
            "id": "awXftV7bUuzsNyZYxFaWo",
            "name": "ILCG_UPLOAD_GOAL_IMAGE_API"
          }
        }
      }
    }
  ],
  "csrf": "0.41hskwbvoipt_Ja7fMLrFhHvcqe4xw5K",
  "_id": "ubu7QFHnybdSEKYD2Pn4X",
  "updatedAt": "4/2/2024",
  "createdAt": "4/2/2024",
  "createdBy": "mubashar",
  "updatedBy": "mubashar"
}
