{
  "id": "MGA6QH17Hn6oawDUd5e3Q",
  "_id": "agznRO4ZGhSBXRZrLmsry",
  "name": "ILP_DELETE_LATER_FIVE",
  "old_name": "ILP_DELETE_LATER_FIVE",
  "projectId": "652fcbce09869c3c809b3097",
  "gitBranchName": "master",
  "services": [
    {
      "type": "11",
      "command": {
        "type": "15",
        "attributes": {
          "requestBody": [],
          "storeType": "",
          "selectedObjectBindingKey": "selectedObject",
          "dataType": "",
          "sourceBindingKey": "",
          "filterList": [
            {
              "key": "ILP_LIST_DATA",
              "changeValueConditonally": false,
              "storeType": 2,
              "logic": {
                "taskFamily": [
                  {
                    "name": "Ahmed Ali",
                    "relationship": "Father",
                    "taskAssigned": "15 Task",
                    "gContributions": "BHD 295.00",
                    "family": [
                      {
                        "name": "Jack Sparrow",
                        "image": "http://172.16.11.67:9996/652fcbce09869c3c809b3097/web/passkey01.svg"
                      }
                    ]
                  },
                  {
                    "name": "Ahmed Ali",
                    "relationship": "Father",
                    "taskAssigned": "15 Task",
                    "gContributions": "BHD 295.00"
                  },
                  {
                    "name": "Raza Hassan",
                    "relationship": "Uncle",
                    "taskAssigned": "05 Task",
                    "gContributions": "BHD 100.00"
                  },
                  {
                    "name": "Memoona Ali",
                    "relationship": "Mom",
                    "taskAssigned": "10 Task",
                    "gContributions": "BHD 200.00"
                  },
                  {
                    "name": "Muhammad Talha",
                    "relationship": "Brother",
                    "taskAssigned": "20 Task",
                    "gContributions": "BHD 395.00"
                  },
                  {
                    "name": "Haider Ali",
                    "relationship": "Uncle",
                    "taskAssigned": "07 Task",
                    "gContributions": "BHD 113.00"
                  },
                  {
                    "name": "Hussain Ali",
                    "relationship": "Uncle",
                    "taskAssigned": "11 Task",
                    "gContributions": "BHD 330.00"
                  },
                  {
                    "name": "Hassan Ali",
                    "relationship": "Father",
                    "taskAssigned": "05 Task",
                    "gContributions": "BHD 120.00"
                  },
                  {
                    "name": "Muhammad Farooq",
                    "relationship": "Father",
                    "taskAssigned": "05 Task",
                    "gContributions": "BHD 109.00"
                  },
                  {
                    "name": "Sara Ahmed",
                    "relationship": "Aunt",
                    "taskAssigned": "13 Task",
                    "gContributions": "BHD 350.00"
                  }
                ]
              }
            }
          ]
        }
      }
    }
  ],
  "csrf": "0.4bjadjd1hnvf3futSNbrD-al1G-qfFyJ",
  "updatedAt": "2/29/2024",
  "createdAt": "2/29/2024",
  "createdBy": "talha",
  "updatedBy": "talha"
}
