{
  "id": "AyNsx6UiPeIL4vLkJCLrc",
  "name": "ILPT_EDIT_WEEKLY_SUNDAY",
  "projectId": "652fcbce09869c3c809b3097",
  "gitBranchName": "master",
  "services": [
    {
      "type": "11",
      "command": {
        "type": "15",
        "attributes": {
          "storeType": "",
          "selectedObjectBindingKey": "selectedObject",
          "dataType": "",
          "sourceBindingKey": "",
          "filterList": [
            {
              "key": "ilpt_weekly_edit_day.name",
              "changeValueConditonally": false,
              "storeType": 1,
              "logic": "Sunday"
            },
            {
              "storeType": 1,
              "key": "ilpt_weekly_edit_day.code",
              "logic": "Sunday"
            }
          ]
        }
      }
    }
  ],
  "csrf": "0.bryqgbnrb21IZaS_rk1qwPvlg_2FB41",
  "_id": "h4ov59TvSC71czPHo68Nq",
  "updatedAt": "4/6/2024",
  "createdAt": "4/6/2024",
  "createdBy": "basitahmed1199",
  "updatedBy": "basitahmed1199"
}
