[
  {
    "id": "wYstieIax08QyNh2Qp4Bd",
    "name": "PC_SUCCESS_MODAL",
    "type": "10001",
    "attributes": {
      "gridProps": [
        {
          "componentId": "3wt84Gy6HQayNrk0jg9vm",
          "componentType": "10001",
          "id": "3wt84Gy6HQayNrk0jg9vm",
          "position": {
            "i": "3wt84Gy6HQayNrk0jg9vm",
            "x": null,
            "y": null,
            "w": null,
            "h": null
          },
          "layoutProperties": { "lg": 12, "md": 12, "sm": 12, "xs": 12 }
        }
      ]
    },
    "layout": [
      {
        "id": "3wt84Gy6HQayNrk0jg9vm",
        "status": "ACTIVE",
        "_id": "610134a1d1f5e860b1e8c751",
        "name": "Grid layout",
        "icon": "FaGripHorizontal",
        "attributes": {
          "gridProps": [],
          "label": "Header",
          "layoutProperties": {
            "gridLayout": {
              "//": "Use this class to style grid layout component.",
              "padding": "5px",
              "spacing": 0
            },
            "mainContainer": "gridLayout"
          },
          "layoutProps": {
            "direction": "row",
            "justifyContent": "flex-start",
            "alignItems": "flex-start"
          },
          "direction": "row",
          "name": "PC_SUCCESS_MODAL",
          "cssClassNames": [{ "cssClassName": "PC_SUCCESS_MAIN " }]
        },
        "group": "Layout",
        "type": "10001",
        "updatedAt": "23-Sep-2021",
        "Documentation": "<div>\n<table style=\"border-collapse: collapse; width: 99.8899%;\" border=\"1\">\n<tbody>\n<tr>\n<td style=\"width: 48.4024%;\">1</td>\n<td style=\"width: 48.4024%;\">&nbsp;</td>\n</tr>\n<tr>\n<td style=\"width: 48.4024%;\">2</td>\n<td style=\"width: 48.4024%;\">&nbsp;</td>\n</tr>\n<tr>\n<td style=\"width: 48.4024%;\">43</td>\n<td style=\"width: 48.4024%;\">&nbsp;</td>\n</tr>\n<tr>\n<td style=\"width: 48.4024%;\">6</td>\n<td style=\"width: 48.4024%;\">&nbsp;</td>\n</tr>\n<tr>\n<td style=\"width: 48.4024%;\">7</td>\n<td style=\"width: 48.4024%;\">&nbsp;</td>\n</tr>\n</tbody>\n</table>\nWrite your Docu7mentationtestsdfasd</div>",
        "createdAt": "24-Aug-2021",
        "events": [],
        "order": 1,
        "version": "1.0.0",
        "isLatest": true,
        "projectType": "web",
        "allowedContainers": ["10001", "20030", "noLayout", "20010", "widget"],
        "component": { "content": "Grid layout", "type": "10001" },
        "path": "0",
        "gridProps": [
          {
            "type": "column",
            "id": "ROpQRhE8s3F6TiHo7vaVH",
            "gridProps": [
              {
                "type": "10001",
                "name": "Grid layout",
                "id": "RQ_x7hmKEtsMsp8MChc46",
                "gridProps": [
                  {
                    "type": "column",
                    "id": "xyzxMKgg7eV1kPcYOKICz",
                    "gridProps": [
                      {
                        "id": "7Aw6cpfc6o-So6Ty0dGno",
                        "status": "ACTIVE",
                        "name": "Image",
                        "icon": "FaImage",
                        "attributes": {
                          "name": "Image",
                          "contentType": false,
                          "defaultImageAssetIdTemp": {
                            "name": "dracaena-cinnabari.jpg",
                            "id": "CNIz67fi824LHr0ae-pOV"
                          },
                          "layoutProperties": {
                            "image": {
                              "//": "Use this class to style image component."
                            },
                            "mainContainer": "image",
                            "xl": 12,
                            "lg": 12,
                            "md": 12,
                            "sm": 12,
                            "xs": 12
                          },
                          "defaultImageAssetId": "CNIz67fi824LHr0ae-pOV",
                          "imageAssetIdTemp": {
                            "createdBy": "user",
                            "_id": "659fb17887797c28bc6eabe0",
                            "name": "confirmation_success.png",
                            "type": "png",
                            "projectId": "652fcbce09869c3c809b3097",
                            "id": "WV75Y8fs8dlTXUpY7VD4D",
                            "gitBranchName": "master",
                            "folderType": "web",
                            "platform": "web",
                            "url": "652fcbce09869c3c809b3097/web/confirmation_success.png",
                            "canvasUrl": "652fcbce09869c3c809b3097/web/confirmation_success.png",
                            "createdAt": "2024-01-11T09:14:32.911Z",
                            "updatedAt": "2024-01-11T09:14:32.911Z",
                            "__v": 0,
                            "uri": "652fcbce09869c3c809b3097/web/confirmation_success.png"
                          },
                          "imageAssetId": "WV75Y8fs8dlTXUpY7VD4D",
                          "stateName": null,
                          "storeType": null,
                          "useFullLink": null,
                          "cssClassNames": [
                            { "cssClassName": "PC_SUCCESS_MODAL_LOGO " }
                          ]
                        },
                        "group": "Form",
                        "updatedAt": "23-Aug-2021",
                        "createdAt": "23-Aug-2021",
                        "order": 0,
                        "type": "20012",
                        "version": "1.0.0",
                        "isLatest": true,
                        "projectType": "web",
                        "component": { "content": "Image", "type": "20012" },
                        "events": [],
                        "path": "0-0-0-0-0"
                      }
                    ],
                    "layoutProperties": {
                      "xl": 12,
                      "lg": 12,
                      "md": 12,
                      "sm": 12,
                      "xs": 12
                    }
                  }
                ],
                "allowedContainers": [
                  "10001",
                  "20030",
                  "noLayout",
                  "20010",
                  "widget"
                ],
                "attributes": {
                  "gridProps": [],
                  "label": "Header",
                  "layoutProperties": {
                    "gridLayout": {
                      "//": "Use this class to style grid layout component.",
                      "padding": "5px",
                      "spacing": 0
                    },
                    "mainContainer": "gridLayout"
                  },
                  "layoutProps": {
                    "direction": "row",
                    "justifyContent": "flex-start",
                    "alignItems": "flex-start"
                  },
                  "direction": "row",
                  "name": "Grid layout"
                },
                "events": [],
                "component": { "type": "10001", "content": "Grid layout" }
              },
              {
                "type": "10001",
                "name": "Grid layout",
                "id": "8a3fD31dRUwnjSFd0t8p3",
                "gridProps": [
                  {
                    "type": "column",
                    "id": "5xi0fKkIC7PPaH0PNhcLK",
                    "gridProps": [
                      {
                        "id": "O-1grnUvFePcCSA5lxbJa",
                        "status": "ACTIVE",
                        "name": "Label",
                        "attributes": {
                          "variant": "body1",
                          "name": "Label",
                          "mandatory": false,
                          "layoutProperties": {
                            "label": {
                              "//": "Use this class to style label component."
                            },
                            "mainContainer": "label",
                            "xl": 12,
                            "lg": 12,
                            "md": 12,
                            "sm": 12,
                            "xs": 12
                          },
                          "label": "Payment received",
                          "cssClassNames": [
                            { "cssClassName": "PC_SUCCESS_TITLE " }
                          ]
                        },
                        "icon": "FaFont",
                        "group": "Form",
                        "type": "20002",
                        "updatedAt": "23-Aug-2021",
                        "createdAt": "23-Aug-2021",
                        "order": 15,
                        "version": "1.0.0",
                        "isLatest": true,
                        "projectType": "web",
                        "component": { "content": "Label", "type": "20002" },
                        "events": [],
                        "path": "0-0-1-0-0"
                      },
                      {
                        "id": "JR_nHwASKpJWvtcTPTqeR",
                        "status": "ACTIVE",
                        "name": "Label",
                        "attributes": {
                          "variant": "body1",
                          "name": "Label",
                          "mandatory": false,
                          "layoutProperties": {
                            "label": {
                              "//": "Use this class to style label component.",
                              "margin-top": "20px"
                            },
                            "mainContainer": "label",
                            "xl": 12,
                            "lg": 12,
                            "md": 12,
                            "sm": 12,
                            "xs": 12
                          },
                          "label": "Your payment was received successfully.",
                          "cssClassNames": [
                            {
                              "cssClassName": "PC_SUCCESS_MODAL_BODY ",
                              "key": "PC_SUCCESS_MODAL_BODY "
                            },
                            {
                              "cssClassName": "Font-Montserrat-Regular ",
                              "key": "Font-Montserrat-Regular "
                            }
                          ]
                        },
                        "icon": "FaFont",
                        "group": "Form",
                        "type": "20002",
                        "updatedAt": "23-Aug-2021",
                        "createdAt": "23-Aug-2021",
                        "order": 15,
                        "version": "1.0.0",
                        "isLatest": true,
                        "projectType": "web",
                        "component": { "content": "Label", "type": "20002" },
                        "events": [],
                        "path": "0-0-1-0-1"
                      },
                      {
                        "id": "-r4Xs8pP6Ee6-O2TESGLr",
                        "status": "ACTIVE",
                        "name": "Label",
                        "attributes": {
                          "variant": "body1",
                          "name": "Label",
                          "mandatory": false,
                          "layoutProperties": {
                            "label": {
                              "//": "Use this class to style label component."
                            },
                            "mainContainer": "label",
                            "xl": 12,
                            "lg": 12,
                            "md": 12,
                            "sm": 12,
                            "xs": 12
                          },
                          "label": "pc_release_payment.content.reference",
                          "prefix": "Reference: ",
                          "searchInState": true,
                          "storeType": 2,
                          "cssClassNames": [
                            { "cssClassName": "PC_SUCCESS_MODAL_MESSAGE " }
                          ]
                        },
                        "icon": "FaFont",
                        "group": "Form",
                        "type": "20002",
                        "updatedAt": "23-Aug-2021",
                        "createdAt": "23-Aug-2021",
                        "order": 15,
                        "version": "1.0.0",
                        "isLatest": true,
                        "projectType": "web",
                        "component": { "content": "Label", "type": "20002" },
                        "events": [],
                        "path": "0-0-1-0-2"
                      }
                    ],
                    "layoutProperties": {
                      "xl": 12,
                      "lg": 12,
                      "md": 12,
                      "sm": 12,
                      "xs": 12
                    }
                  }
                ],
                "allowedContainers": [
                  "10001",
                  "20030",
                  "noLayout",
                  "20010",
                  "widget"
                ],
                "attributes": {
                  "gridProps": [],
                  "label": "Header",
                  "layoutProperties": {
                    "gridLayout": {
                      "//": "Use this class to style grid layout component.",
                      "padding": "5px",
                      "spacing": 0
                    },
                    "mainContainer": "gridLayout"
                  },
                  "layoutProps": {
                    "direction": "row",
                    "justifyContent": "flex-start",
                    "alignItems": "flex-start"
                  },
                  "direction": "row",
                  "name": "Grid layout"
                },
                "events": [],
                "component": { "type": "10001", "content": "Grid layout" }
              },
              {
                "type": "10001",
                "name": "Grid layout",
                "id": "9QGIv-RAHTZp22793CaQz",
                "gridProps": [
                  {
                    "type": "column",
                    "id": "PHobM6efLn_-fD--tGqoh",
                    "gridProps": [
                      {
                        "id": "cHRezGuRaGwX__x8Wnx7P",
                        "type": "20006",
                        "name": "Button",
                        "component": { "content": "Button", "type": "20006" },
                        "attributes": {
                          "label": "Done",
                          "variant": "contained",
                          "name": "Button",
                          "label-locale-key": "",
                          "fullWidth": true,
                          "layoutProperties": {
                            "button": {
                              "//": "Use this class to style button component.",
                              "text-transform": "capitalize",
                              "width": "100%"
                            },
                            "iconButton": {
                              "//": "Use this class to style icon button component.",
                              "width": "20px",
                              "height": "20px"
                            },
                            "inputProps": {
                              "//": "Use this class to style button element."
                            },
                            "mainContainer": "button",
                            "xl": 12,
                            "lg": 12,
                            "md": 12,
                            "sm": 12,
                            "xs": 12
                          },
                          "cssClassNames": [
                            {
                              "cssClassName": "GENERIC_PRIMARY_BUTTON ",
                              "key": "GENERIC_PRIMARY_BUTTON "
                            }
                          ]
                        },
                        "events": [
                          {
                            "triggerId": "WuhHxg90Z2anPz7DGsIrC",
                            "triggerName": "Close Modal",
                            "serviceType": "9",
                            "attributes": {
                              "content": "",
                              "type": "",
                              "modalId": "ozKeLAA5SQp3bjJ9kCQQg",
                              "toastContentType": "custom"
                            },
                            "type": "2",
                            "name": "On click",
                            "commandType": "2"
                          }
                        ],
                        "path": "0-0-2-0-0",
                        "version": "1.0.0"
                      }
                    ],
                    "layoutProperties": {
                      "xl": 12,
                      "lg": 12,
                      "md": 12,
                      "sm": 12,
                      "xs": 12
                    }
                  }
                ],
                "allowedContainers": [
                  "10001",
                  "20030",
                  "noLayout",
                  "20010",
                  "widget"
                ],
                "attributes": {
                  "gridProps": [],
                  "label": "Header",
                  "layoutProperties": {
                    "gridLayout": {
                      "//": "Use this class to style grid layout component.",
                      "spacing": 0,
                      "padding": "24px"
                    },
                    "mainContainer": "gridLayout",
                    "skeleton": {
                      "//": "Use this class to style skeleton loading component."
                    },
                    "imageStyles": {
                      "//": "Use this class to style image component."
                    }
                  },
                  "layoutProps": {
                    "direction": "row",
                    "justifyContent": "flex-start",
                    "alignItems": "flex-start"
                  },
                  "direction": "row",
                  "name": "Grid layout"
                },
                "events": [],
                "component": { "type": "10001", "content": "Grid layout" },
                "path": "0-0-2",
                "dimensions": {
                  "rows": 1,
                  "columns": 1,
                  "colSize0xs": 12,
                  "colSize0sm": 12,
                  "colSize0md": 12,
                  "colSize0lg": 12,
                  "colSize0xl": 12
                },
                "readOnly": true
              }
            ],
            "layoutProperties": {
              "xl": 12,
              "lg": 12,
              "md": 12,
              "sm": 12,
              "xs": 12
            }
          }
        ],
        "layoutProperties": { "lg": 12, "md": 12, "sm": 12, "xs": 12 }
      }
    ],
    "events": [],
    "subType": "widget",
    "screenId": "wYstieIax08QyNh2Qp4Bd",
    "projectId": "652fcbce09869c3c809b3097",
    "version": "1.0.0",
    "gitBranchName": "master",
    "_id": "wYstieIax08QyNh2Qp4Bd",
    "createdBy": "kelashk",
    "updatedAt": "8/13/2024",
    "createdAt": "8/13/2024",
    "updatedTimestamp": "0000-00-00T00:00:00+00:00"
  },
  {
    "id": "3wt84Gy6HQayNrk0jg9vm",
    "name": "Grid layout",
    "type": "10001",
    "attributes": {
      "gridProps": [
        {
          "componentId": "RQ_x7hmKEtsMsp8MChc46",
          "componentType": "10001",
          "id": "RQ_x7hmKEtsMsp8MChc46",
          "position": {
            "i": "RQ_x7hmKEtsMsp8MChc46",
            "x": null,
            "y": null,
            "w": null,
            "h": null
          },
          "layoutProperties": {
            "xl": 12,
            "lg": 12,
            "md": 12,
            "sm": 12,
            "xs": 12
          }
        },
        {
          "componentId": "8a3fD31dRUwnjSFd0t8p3",
          "componentType": "10001",
          "id": "8a3fD31dRUwnjSFd0t8p3",
          "position": {
            "i": "8a3fD31dRUwnjSFd0t8p3",
            "x": null,
            "y": null,
            "w": null,
            "h": null
          },
          "layoutProperties": {
            "xl": 12,
            "lg": 12,
            "md": 12,
            "sm": 12,
            "xs": 12
          }
        },
        {
          "componentId": "9QGIv-RAHTZp22793CaQz",
          "componentType": "10001",
          "id": "9QGIv-RAHTZp22793CaQz",
          "position": {
            "i": "9QGIv-RAHTZp22793CaQz",
            "x": null,
            "y": null,
            "w": null,
            "h": null
          },
          "layoutProperties": {
            "xl": 12,
            "lg": 12,
            "md": 12,
            "sm": 12,
            "xs": 12
          }
        }
      ],
      "label": "Header",
      "layoutProperties": {
        "gridLayout": {
          "//": "Use this class to style grid layout component.",
          "padding": "5px",
          "spacing": 0
        },
        "mainContainer": "gridLayout"
      },
      "layoutProps": {
        "direction": "row",
        "justifyContent": "flex-start",
        "alignItems": "flex-start"
      },
      "direction": "row",
      "name": "PC_SUCCESS_MODAL",
      "cssClassNames": [{ "cssClassName": "PC_SUCCESS_MAIN " }]
    },
    "layout": null,
    "events": [],
    "subType": "component",
    "screenId": "wYstieIax08QyNh2Qp4Bd",
    "projectId": "652fcbce09869c3c809b3097",
    "version": "1.0.0",
    "gitBranchName": "master",
    "createdBy": "kelashk",
    "updatedAt": "8/13/2024",
    "createdAt": "8/13/2024",
    "updatedTimestamp": "0000-00-00T00:00:00+00:00"
  },
  {
    "id": "RQ_x7hmKEtsMsp8MChc46",
    "name": "Grid layout",
    "type": "10001",
    "attributes": {
      "gridProps": [
        {
          "layoutProperties": {
            "xl": 12,
            "lg": 12,
            "md": 12,
            "sm": 12,
            "xs": 12
          },
          "componentId": "7Aw6cpfc6o-So6Ty0dGno",
          "componentType": "20012",
          "order": 1
        }
      ],
      "label": "Header",
      "layoutProperties": {
        "gridLayout": {
          "//": "Use this class to style grid layout component.",
          "padding": "5px",
          "spacing": 0
        },
        "mainContainer": "gridLayout"
      },
      "layoutProps": {
        "direction": "row",
        "justifyContent": "flex-start",
        "alignItems": "flex-start"
      },
      "direction": "row",
      "name": "Grid layout"
    },
    "layout": null,
    "events": [],
    "subType": "component",
    "screenId": "wYstieIax08QyNh2Qp4Bd",
    "projectId": "652fcbce09869c3c809b3097",
    "version": "1.0.0",
    "gitBranchName": "master",
    "createdBy": "kelashk",
    "updatedAt": "8/13/2024",
    "createdAt": "8/13/2024",
    "updatedTimestamp": "0000-00-00T00:00:00+00:00"
  },
  {
    "id": "7Aw6cpfc6o-So6Ty0dGno",
    "status": "ACTIVE",
    "name": "Image",
    "icon": "FaImage",
    "attributes": {
      "name": "Image",
      "contentType": false,
      "defaultImageAssetIdTemp": {
        "name": "dracaena-cinnabari.jpg",
        "id": "CNIz67fi824LHr0ae-pOV"
      },
      "layoutProperties": {
        "image": { "//": "Use this class to style image component." },
        "mainContainer": "image",
        "xl": 12,
        "lg": 12,
        "md": 12,
        "sm": 12,
        "xs": 12
      },
      "defaultImageAssetId": "CNIz67fi824LHr0ae-pOV",
      "imageAssetIdTemp": {
        "createdBy": "user",
        "_id": "659fb17887797c28bc6eabe0",
        "name": "confirmation_success.png",
        "type": "png",
        "projectId": "652fcbce09869c3c809b3097",
        "id": "WV75Y8fs8dlTXUpY7VD4D",
        "gitBranchName": "master",
        "folderType": "web",
        "platform": "web",
        "url": "652fcbce09869c3c809b3097/web/confirmation_success.png",
        "canvasUrl": "652fcbce09869c3c809b3097/web/confirmation_success.png",
        "createdAt": "2024-01-11T09:14:32.911Z",
        "updatedAt": "2024-01-11T09:14:32.911Z",
        "__v": 0,
        "uri": "652fcbce09869c3c809b3097/web/confirmation_success.png"
      },
      "imageAssetId": "WV75Y8fs8dlTXUpY7VD4D",
      "stateName": null,
      "storeType": null,
      "useFullLink": null,
      "cssClassNames": [{ "cssClassName": "PC_SUCCESS_MODAL_LOGO " }]
    },
    "group": "Form",
    "updatedAt": "8/13/2024",
    "createdAt": "8/13/2024",
    "order": 0,
    "type": "20012",
    "version": "1.0.0",
    "isLatest": true,
    "projectType": "web",
    "component": { "content": "Image", "type": "20012" },
    "events": [],
    "path": "0-0-0-0-0",
    "screenId": "wYstieIax08QyNh2Qp4Bd",
    "subType": "component",
    "projectId": "652fcbce09869c3c809b3097",
    "gitBranchName": "master",
    "createdBy": "kelashk",
    "updatedTimestamp": "0000-00-00T00:00:00+00:00"
  },
  {
    "id": "8a3fD31dRUwnjSFd0t8p3",
    "name": "Grid layout",
    "type": "10001",
    "attributes": {
      "gridProps": [
        {
          "layoutProperties": {
            "xl": 12,
            "lg": 12,
            "md": 12,
            "sm": 12,
            "xs": 12
          },
          "componentId": "O-1grnUvFePcCSA5lxbJa",
          "componentType": "20002",
          "order": 1
        },
        {
          "layoutProperties": {
            "xl": 12,
            "lg": 12,
            "md": 12,
            "sm": 12,
            "xs": 12
          },
          "componentId": "JR_nHwASKpJWvtcTPTqeR",
          "componentType": "20002",
          "order": 1
        },
        {
          "layoutProperties": {
            "xl": 12,
            "lg": 12,
            "md": 12,
            "sm": 12,
            "xs": 12
          },
          "componentId": "-r4Xs8pP6Ee6-O2TESGLr",
          "componentType": "20002",
          "order": 1
        }
      ],
      "label": "Header",
      "layoutProperties": {
        "gridLayout": {
          "//": "Use this class to style grid layout component.",
          "padding": "5px",
          "spacing": 0
        },
        "mainContainer": "gridLayout"
      },
      "layoutProps": {
        "direction": "row",
        "justifyContent": "flex-start",
        "alignItems": "flex-start"
      },
      "direction": "row",
      "name": "Grid layout"
    },
    "layout": null,
    "events": [],
    "subType": "component",
    "screenId": "wYstieIax08QyNh2Qp4Bd",
    "projectId": "652fcbce09869c3c809b3097",
    "version": "1.0.0",
    "gitBranchName": "master",
    "createdBy": "kelashk",
    "updatedAt": "8/13/2024",
    "createdAt": "8/13/2024",
    "updatedTimestamp": "0000-00-00T00:00:00+00:00"
  },
  {
    "id": "O-1grnUvFePcCSA5lxbJa",
    "status": "ACTIVE",
    "name": "Label",
    "attributes": {
      "variant": "body1",
      "name": "Label",
      "mandatory": false,
      "layoutProperties": {
        "label": { "//": "Use this class to style label component." },
        "mainContainer": "label",
        "xl": 12,
        "lg": 12,
        "md": 12,
        "sm": 12,
        "xs": 12
      },
      "label": "Payment received",
      "cssClassNames": [{ "cssClassName": "PC_SUCCESS_TITLE " }]
    },
    "icon": "FaFont",
    "group": "Form",
    "type": "20002",
    "updatedAt": "8/13/2024",
    "createdAt": "8/13/2024",
    "order": 15,
    "version": "1.0.0",
    "isLatest": true,
    "projectType": "web",
    "component": { "content": "Label", "type": "20002" },
    "events": [],
    "path": "0-0-1-0-0",
    "screenId": "wYstieIax08QyNh2Qp4Bd",
    "subType": "component",
    "projectId": "652fcbce09869c3c809b3097",
    "gitBranchName": "master",
    "createdBy": "kelashk",
    "updatedTimestamp": "0000-00-00T00:00:00+00:00"
  },
  {
    "id": "JR_nHwASKpJWvtcTPTqeR",
    "status": "ACTIVE",
    "name": "Label",
    "attributes": {
      "variant": "body1",
      "name": "Label",
      "mandatory": false,
      "layoutProperties": {
        "label": {
          "//": "Use this class to style label component.",
          "margin-top": "20px"
        },
        "mainContainer": "label",
        "xl": 12,
        "lg": 12,
        "md": 12,
        "sm": 12,
        "xs": 12
      },
      "label": "Your payment was received successfully.",
      "cssClassNames": [
        {
          "cssClassName": "PC_SUCCESS_MODAL_BODY ",
          "key": "PC_SUCCESS_MODAL_BODY "
        },
        {
          "cssClassName": "Font-Montserrat-Regular ",
          "key": "Font-Montserrat-Regular "
        }
      ]
    },
    "icon": "FaFont",
    "group": "Form",
    "type": "20002",
    "updatedAt": "8/13/2024",
    "createdAt": "8/13/2024",
    "order": 15,
    "version": "1.0.0",
    "isLatest": true,
    "projectType": "web",
    "component": { "content": "Label", "type": "20002" },
    "events": [],
    "path": "0-0-1-0-1",
    "screenId": "wYstieIax08QyNh2Qp4Bd",
    "subType": "component",
    "projectId": "652fcbce09869c3c809b3097",
    "gitBranchName": "master",
    "createdBy": "kelashk",
    "updatedTimestamp": "0000-00-00T00:00:00+00:00"
  },
  {
    "id": "-r4Xs8pP6Ee6-O2TESGLr",
    "status": "ACTIVE",
    "name": "Label",
    "attributes": {
      "variant": "body1",
      "name": "Label",
      "mandatory": false,
      "layoutProperties": {
        "label": { "//": "Use this class to style label component." },
        "mainContainer": "label",
        "xl": 12,
        "lg": 12,
        "md": 12,
        "sm": 12,
        "xs": 12
      },
      "label": "pc_release_payment.content.reference",
      "prefix": "Reference: ",
      "searchInState": true,
      "storeType": 2,
      "cssClassNames": [{ "cssClassName": "PC_SUCCESS_MODAL_MESSAGE " }]
    },
    "icon": "FaFont",
    "group": "Form",
    "type": "20002",
    "updatedAt": "8/13/2024",
    "createdAt": "8/13/2024",
    "order": 15,
    "version": "1.0.0",
    "isLatest": true,
    "projectType": "web",
    "component": { "content": "Label", "type": "20002" },
    "events": [],
    "path": "0-0-1-0-2",
    "screenId": "wYstieIax08QyNh2Qp4Bd",
    "subType": "component",
    "projectId": "652fcbce09869c3c809b3097",
    "gitBranchName": "master",
    "createdBy": "kelashk",
    "updatedTimestamp": "0000-00-00T00:00:00+00:00"
  },
  {
    "id": "9QGIv-RAHTZp22793CaQz",
    "name": "Grid layout",
    "type": "10001",
    "attributes": {
      "gridProps": [
        {
          "layoutProperties": {
            "xl": 12,
            "lg": 12,
            "md": 12,
            "sm": 12,
            "xs": 12
          },
          "componentId": "cHRezGuRaGwX__x8Wnx7P",
          "componentType": "20006",
          "order": 1
        }
      ],
      "label": "Header",
      "layoutProperties": {
        "gridLayout": {
          "//": "Use this class to style grid layout component.",
          "spacing": 0,
          "padding": "24px"
        },
        "mainContainer": "gridLayout",
        "skeleton": {
          "//": "Use this class to style skeleton loading component."
        },
        "imageStyles": { "//": "Use this class to style image component." }
      },
      "layoutProps": {
        "direction": "row",
        "justifyContent": "flex-start",
        "alignItems": "flex-start"
      },
      "direction": "row",
      "name": "Grid layout"
    },
    "layout": null,
    "events": [],
    "subType": "component",
    "screenId": "wYstieIax08QyNh2Qp4Bd",
    "projectId": "652fcbce09869c3c809b3097",
    "version": "1.0.0",
    "gitBranchName": "master",
    "createdBy": "kelashk",
    "updatedAt": "8/13/2024",
    "createdAt": "8/13/2024",
    "updatedTimestamp": "0000-00-00T00:00:00+00:00"
  },
  {
    "id": "cHRezGuRaGwX__x8Wnx7P",
    "type": "20006",
    "name": "Button",
    "component": { "content": "Button", "type": "20006" },
    "attributes": {
      "label": "Done",
      "variant": "contained",
      "name": "Button",
      "label-locale-key": "",
      "fullWidth": true,
      "layoutProperties": {
        "button": {
          "//": "Use this class to style button component.",
          "text-transform": "capitalize",
          "width": "100%"
        },
        "iconButton": {
          "//": "Use this class to style icon button component.",
          "width": "20px",
          "height": "20px"
        },
        "inputProps": { "//": "Use this class to style button element." },
        "mainContainer": "button",
        "xl": 12,
        "lg": 12,
        "md": 12,
        "sm": 12,
        "xs": 12
      },
      "cssClassNames": [
        {
          "cssClassName": "GENERIC_PRIMARY_BUTTON ",
          "key": "GENERIC_PRIMARY_BUTTON "
        }
      ]
    },
    "events": [
      {
        "triggerId": "WuhHxg90Z2anPz7DGsIrC",
        "triggerName": "Close Modal",
        "name": "On click",
        "type": "2",
        "serviceType": "9"
      }
    ],
    "path": "0-0-2-0-0",
    "version": "1.0.0",
    "screenId": "wYstieIax08QyNh2Qp4Bd",
    "subType": "component",
    "projectId": "652fcbce09869c3c809b3097",
    "gitBranchName": "master",
    "createdBy": "kelashk",
    "updatedAt": "8/13/2024",
    "createdAt": "8/13/2024",
    "updatedTimestamp": "0000-00-00T00:00:00+00:00"
  }
]
