[
  {
    "id": "aVkTpUBXJduhU3Pcihr6b",
    "name": "SERVICE-CARD_TAB_WIDGET",
    "type": "10001",
    "attributes": {
      "gridProps": [
        {
          "componentId": "C38wVPsshIMSLN5UDrfGB",
          "componentType": "10001",
          "id": "C38wVPsshIMSLN5UDrfGB",
          "position": {
            "i": "C38wVPsshIMSLN5UDrfGB",
            "x": null,
            "y": null,
            "w": null,
            "h": null
          },
          "layoutProperties": { "lg": 12, "md": 12, "sm": 12, "xs": 12 }
        }
      ]
    },
    "layout": [
      {
        "id": "C38wVPsshIMSLN5UDrfGB",
        "status": "ACTIVE",
        "_id": "610134a1d1f5e860b1e8c751",
        "name": "Grid layout",
        "icon": "FaGripHorizontal",
        "attributes": {
          "gridProps": [],
          "label": "Header",
          "layoutProperties": {
            "gridLayout": {
              "//": "Use this class to style grid layout component.",
              "padding": "5px",
              "spacing": 0
            },
            "mainContainer": "gridLayout"
          },
          "layoutProps": {
            "direction": "row",
            "justifyContent": "flex-start",
            "alignItems": "flex-start"
          },
          "direction": "row",
          "name": "Grid layout"
        },
        "group": "Layout",
        "type": "sidebarItem",
        "updatedAt": "23-Sep-2021",
        "Documentation": "<div>\n<table style=\"border-collapse: collapse; width: 99.8899%;\" border=\"1\">\n<tbody>\n<tr>\n<td style=\"width: 48.4024%;\">1</td>\n<td style=\"width: 48.4024%;\">&nbsp;</td>\n</tr>\n<tr>\n<td style=\"width: 48.4024%;\">2</td>\n<td style=\"width: 48.4024%;\">&nbsp;</td>\n</tr>\n<tr>\n<td style=\"width: 48.4024%;\">43</td>\n<td style=\"width: 48.4024%;\">&nbsp;</td>\n</tr>\n<tr>\n<td style=\"width: 48.4024%;\">6</td>\n<td style=\"width: 48.4024%;\">&nbsp;</td>\n</tr>\n<tr>\n<td style=\"width: 48.4024%;\">7</td>\n<td style=\"width: 48.4024%;\">&nbsp;</td>\n</tr>\n</tbody>\n</table>\nWrite your Docu7mentationtestsdfasd</div>",
        "createdAt": "24-Aug-2021",
        "events": [],
        "order": 1,
        "version": "1.0.0",
        "isLatest": true,
        "projectType": "web",
        "allowedContainers": ["10001", "20030", "noLayout", "20010", "widget"],
        "component": { "content": "Grid layout", "type": "10001" },
        "path": 0,
        "gridProps": [
          {
            "type": "column",
            "id": "T3WSJDLBauUHJ2pcp3l8n",
            "gridProps": [
              {
                "type": "10001",
                "name": "Grid layout",
                "id": "qnS7jfVsHAjoMv3WizYgO",
                "gridProps": [
                  {
                    "type": "column",
                    "id": "sK_rGtG3UYWpm2QqvlvFX",
                    "gridProps": [],
                    "layoutProperties": {
                      "xl": 12,
                      "lg": 12,
                      "md": 12,
                      "sm": 12,
                      "xs": 12
                    }
                  }
                ],
                "allowedContainers": [
                  "10001",
                  "20030",
                  "noLayout",
                  "20010",
                  "widget"
                ],
                "attributes": {
                  "gridProps": [],
                  "label": "Header",
                  "layoutProperties": {
                    "gridLayout": {
                      "//": "Use this class to style grid layout component.",
                      "padding": "5px",
                      "spacing": 0,
                      "borderRadius": "15px"
                    },
                    "mainContainer": "gridLayout"
                  },
                  "layoutProps": {
                    "direction": "row",
                    "justifyContent": "flex-start",
                    "alignItems": "flex-start"
                  },
                  "direction": "row",
                  "name": "Grid layout"
                },
                "events": [],
                "component": { "type": "10001", "content": "Grid layout" },
                "path": "0-0-0",
                "dimensions": {
                  "rows": 1,
                  "columns": 1,
                  "colSize0xs": 12,
                  "colSize0sm": 12,
                  "colSize0md": 12,
                  "colSize0lg": 12,
                  "colSize0xl": 12
                },
                "readOnly": false
              }
            ],
            "layoutProperties": {
              "xl": 12,
              "lg": 12,
              "md": 12,
              "sm": 12,
              "xs": 12
            },
            "path": "0-0"
          }
        ],
        "layoutProperties": { "lg": 12, "md": 12, "sm": 12, "xs": 12 }
      }
    ],
    "events": [],
    "subType": "widget",
    "screenId": "aVkTpUBXJduhU3Pcihr6b",
    "projectId": "652fcbce09869c3c809b3097",
    "version": "1.0.0",
    "gitBranchName": "master",
    "_id": "aVkTpUBXJduhU3Pcihr6b",
    "createdBy": "muhammad.asad",
    "updatedAt": "12/12/2023",
    "createdAt": "12/12/2023",
    "updatedTimestamp": "0000-00-00T00:00:00+00:00"
  },
  {
    "id": "C38wVPsshIMSLN5UDrfGB",
    "name": "Grid layout",
    "type": "10001",
    "attributes": {
      "gridProps": [
        {
          "componentId": "qnS7jfVsHAjoMv3WizYgO",
          "componentType": "10001",
          "id": "qnS7jfVsHAjoMv3WizYgO",
          "position": {
            "i": "qnS7jfVsHAjoMv3WizYgO",
            "x": null,
            "y": null,
            "w": null,
            "h": null
          },
          "layoutProperties": {
            "xl": 12,
            "lg": 12,
            "md": 12,
            "sm": 12,
            "xs": 12
          }
        }
      ],
      "label": "Header",
      "layoutProperties": {
        "gridLayout": {
          "//": "Use this class to style grid layout component.",
          "padding": "5px",
          "spacing": 0
        },
        "mainContainer": "gridLayout"
      },
      "layoutProps": {
        "direction": "row",
        "justifyContent": "flex-start",
        "alignItems": "flex-start"
      },
      "direction": "row",
      "name": "Grid layout"
    },
    "layout": null,
    "events": [],
    "subType": "component",
    "screenId": "aVkTpUBXJduhU3Pcihr6b",
    "projectId": "652fcbce09869c3c809b3097",
    "version": "1.0.0",
    "gitBranchName": "master",
    "updatedTimestamp": "0000-00-00T00:00:00+00:00"
  },
  {
    "id": "qnS7jfVsHAjoMv3WizYgO",
    "name": "Grid layout",
    "type": "10001",
    "attributes": {
      "gridProps": [],
      "label": "Header",
      "layoutProperties": {
        "gridLayout": {
          "//": "Use this class to style grid layout component.",
          "padding": "5px",
          "spacing": 0,
          "borderRadius": "15px"
        },
        "mainContainer": "gridLayout"
      },
      "layoutProps": {
        "direction": "row",
        "justifyContent": "flex-start",
        "alignItems": "flex-start"
      },
      "direction": "row",
      "name": "Grid layout"
    },
    "layout": null,
    "events": [],
    "subType": "component",
    "screenId": "aVkTpUBXJduhU3Pcihr6b",
    "projectId": "652fcbce09869c3c809b3097",
    "version": "1.0.0",
    "gitBranchName": "master",
    "updatedTimestamp": "0000-00-00T00:00:00+00:00"
  }
]
