[
  {
    "id": "hYVmHpX7q_9c5ft3KAZQ4",
    "name": "TBG_RESPONSE",
    "type": "10001",
    "attributes": {
      "gridProps": [
        {
          "componentId": "cvSg1Z5gK6PqGfzaQpRbe",
          "componentType": "10001",
          "id": "cvSg1Z5gK6PqGfzaQpRbe",
          "position": {
            "i": "cvSg1Z5gK6PqGfzaQpRbe",
            "x": null,
            "y": null,
            "w": null,
            "h": null
          },
          "layoutProperties": { "lg": 12, "md": 12, "sm": 12, "xs": 12 }
        }
      ]
    },
    "layout": [
      {
        "id": "cvSg1Z5gK6PqGfzaQpRbe",
        "status": "ACTIVE",
        "_id": "610134a1d1f5e860b1e8c751",
        "name": "Grid layout",
        "icon": "FaGripHorizontal",
        "attributes": {
          "gridProps": [],
          "label": "Header",
          "layoutProperties": {
            "gridLayout": {
              "//": "Use this class to style grid layout component.",
              "spacing": 0
            },
            "mainContainer": "gridLayout",
            "skeleton": {
              "//": "Use this class to style skeleton loading component."
            }
          },
          "layoutProps": {
            "direction": "row",
            "justifyContent": "flex-start",
            "alignItems": "flex-start"
          },
          "direction": "row",
          "name": "TBG_RESPONSE"
        },
        "group": "Layout",
        "type": "sidebarItem",
        "updatedAt": "23-Sep-2021",
        "Documentation": "<div>\n<table style=\"border-collapse: collapse; width: 99.8899%;\" border=\"1\">\n<tbody>\n<tr>\n<td style=\"width: 48.4024%;\">1</td>\n<td style=\"width: 48.4024%;\">&nbsp;</td>\n</tr>\n<tr>\n<td style=\"width: 48.4024%;\">2</td>\n<td style=\"width: 48.4024%;\">&nbsp;</td>\n</tr>\n<tr>\n<td style=\"width: 48.4024%;\">43</td>\n<td style=\"width: 48.4024%;\">&nbsp;</td>\n</tr>\n<tr>\n<td style=\"width: 48.4024%;\">6</td>\n<td style=\"width: 48.4024%;\">&nbsp;</td>\n</tr>\n<tr>\n<td style=\"width: 48.4024%;\">7</td>\n<td style=\"width: 48.4024%;\">&nbsp;</td>\n</tr>\n</tbody>\n</table>\nWrite your Docu7mentationtestsdfasd</div>",
        "createdAt": "24-Aug-2021",
        "events": [],
        "order": 1,
        "version": "1.0.0",
        "isLatest": true,
        "projectType": "web",
        "allowedContainers": ["10001", "20030", "noLayout", "20010", "widget"],
        "component": { "content": "Grid layout", "type": "10001" },
        "path": 0,
        "gridProps": [
          {
            "type": "column",
            "id": "y1yCAqYzN6m4mQtEz40BX",
            "gridProps": [
              {
                "id": "aiZMz2PZZ_zMx_ea7xbqf",
                "status": "ACTIVE",
                "_id": "610134a1d1f5e860b1e8c751",
                "name": "Grid layout",
                "icon": "FaGripHorizontal",
                "attributes": {
                  "gridProps": [],
                  "label": "Header",
                  "layoutProperties": {
                    "gridLayout": {
                      "//": "Use this class to style grid layout component.",
                      "spacing": 0
                    },
                    "mainContainer": "gridLayout"
                  },
                  "layoutProps": {
                    "direction": "row",
                    "justifyContent": "flex-start",
                    "alignItems": "flex-start"
                  },
                  "direction": "row",
                  "name": "Grid layout"
                },
                "group": "Layout",
                "type": "sidebarItem",
                "updatedAt": "23-Sep-2021",
                "Documentation": "<div>\n<table style=\"border-collapse: collapse; width: 99.8899%;\" border=\"1\">\n<tbody>\n<tr>\n<td style=\"width: 48.4024%;\">1</td>\n<td style=\"width: 48.4024%;\">&nbsp;</td>\n</tr>\n<tr>\n<td style=\"width: 48.4024%;\">2</td>\n<td style=\"width: 48.4024%;\">&nbsp;</td>\n</tr>\n<tr>\n<td style=\"width: 48.4024%;\">43</td>\n<td style=\"width: 48.4024%;\">&nbsp;</td>\n</tr>\n<tr>\n<td style=\"width: 48.4024%;\">6</td>\n<td style=\"width: 48.4024%;\">&nbsp;</td>\n</tr>\n<tr>\n<td style=\"width: 48.4024%;\">7</td>\n<td style=\"width: 48.4024%;\">&nbsp;</td>\n</tr>\n</tbody>\n</table>\nWrite your Docu7mentationtestsdfasd</div>",
                "createdAt": "24-Aug-2021",
                "events": [],
                "order": 1,
                "version": "1.0.0",
                "isLatest": true,
                "projectType": "web",
                "allowedContainers": [
                  "10001",
                  "20030",
                  "noLayout",
                  "20010",
                  "widget"
                ],
                "component": { "content": "Grid layout", "type": "10001" },
                "path": "0-0-0",
                "gridProps": [
                  {
                    "type": "column",
                    "id": "QxrdV4uujYTU6vzsdb53q",
                    "gridProps": [
                      {
                        "id": "iO0q4XZ3NIAgnPkpQbUYO",
                        "status": "ACTIVE",
                        "_id": "610134a1d1f5e860b1e8c751",
                        "name": "TBW_SUCCESS_2",
                        "icon": "FaGripHorizontal",
                        "attributes": {
                          "gridProps": [],
                          "label": "Header",
                          "layoutProperties": {
                            "gridLayout": {
                              "//": "Use this class to style grid layout component.",
                              "spacing": 0
                            },
                            "mainContainer": "gridLayout"
                          },
                          "layoutProps": {
                            "direction": "row",
                            "justifyContent": "flex-start",
                            "alignItems": "flex-start"
                          },
                          "direction": "row",
                          "name": "TBW_SUCCESS_2",
                          "cssClassNames": [
                            { "cssClassName": "PC_SUCCESS_MAIN " }
                          ],
                          "hideCondition": {
                            "logic": {
                              "if": [
                                {
                                  "==": [
                                    {
                                      "var": "currentScreen.tbg_response.code"
                                    },
                                    1
                                  ]
                                },
                                false,
                                true
                              ]
                            }
                          }
                        },
                        "group": "Layout",
                        "type": "10001",
                        "updatedAt": "23-Sep-2021",
                        "Documentation": "<div>\n<table style=\"border-collapse: collapse; width: 99.8899%;\" border=\"1\">\n<tbody>\n<tr>\n<td style=\"width: 48.4024%;\">1</td>\n<td style=\"width: 48.4024%;\">&nbsp;</td>\n</tr>\n<tr>\n<td style=\"width: 48.4024%;\">2</td>\n<td style=\"width: 48.4024%;\">&nbsp;</td>\n</tr>\n<tr>\n<td style=\"width: 48.4024%;\">43</td>\n<td style=\"width: 48.4024%;\">&nbsp;</td>\n</tr>\n<tr>\n<td style=\"width: 48.4024%;\">6</td>\n<td style=\"width: 48.4024%;\">&nbsp;</td>\n</tr>\n<tr>\n<td style=\"width: 48.4024%;\">7</td>\n<td style=\"width: 48.4024%;\">&nbsp;</td>\n</tr>\n</tbody>\n</table>\nWrite your Docu7mentationtestsdfasd</div>",
                        "createdAt": "24-Aug-2021",
                        "events": [],
                        "order": 1,
                        "version": "1.0.0",
                        "isLatest": true,
                        "projectType": "web",
                        "allowedContainers": [
                          "10001",
                          "20030",
                          "noLayout",
                          "20010",
                          "widget"
                        ],
                        "component": {
                          "content": "Grid layout",
                          "type": "10001"
                        },
                        "path": "0-0-0-0-0",
                        "gridProps": [
                          {
                            "type": "column",
                            "id": "BDpowvYjbw9hTzTnBsZZo",
                            "gridProps": [
                              {
                                "type": "10001",
                                "name": "Grid layout",
                                "id": "wtf2SHMxCSObwZ45GCR1r",
                                "gridProps": [
                                  {
                                    "type": "column",
                                    "id": "aaYr3V6Ry4h23YDLSUfCV",
                                    "gridProps": [
                                      {
                                        "id": "b8HUsIht0q-HEFKi0g4Xh",
                                        "status": "ACTIVE",
                                        "name": "Image",
                                        "icon": "FaImage",
                                        "attributes": {
                                          "name": "Image",
                                          "contentType": false,
                                          "defaultImageAssetIdTemp": {
                                            "name": "dracaena-cinnabari.jpg",
                                            "id": "CNIz67fi824LHr0ae-pOV"
                                          },
                                          "layoutProperties": {
                                            "image": {
                                              "//": "Use this class to style image component."
                                            },
                                            "mainContainer": "image",
                                            "xl": 12,
                                            "lg": 12,
                                            "md": 12,
                                            "sm": 12,
                                            "xs": 12
                                          },
                                          "defaultImageAssetId": "CNIz67fi824LHr0ae-pOV",
                                          "imageAssetIdTemp": {
                                            "createdBy": "user",
                                            "_id": "659fb17887797c28bc6eabe0",
                                            "name": "confirmation_success.png",
                                            "type": "png",
                                            "projectId": "652fcbce09869c3c809b3097",
                                            "id": "WV75Y8fs8dlTXUpY7VD4D",
                                            "gitBranchName": "master",
                                            "folderType": "web",
                                            "platform": "web",
                                            "url": "652fcbce09869c3c809b3097/web/confirmation_success.png",
                                            "canvasUrl": "652fcbce09869c3c809b3097/web/confirmation_success.png",
                                            "createdAt": "2024-01-11T09:14:32.911Z",
                                            "updatedAt": "2024-01-11T09:14:32.911Z",
                                            "__v": 0,
                                            "uri": "652fcbce09869c3c809b3097/web/confirmation_success.png"
                                          },
                                          "imageAssetId": "WV75Y8fs8dlTXUpY7VD4D",
                                          "stateName": null,
                                          "storeType": null,
                                          "useFullLink": null,
                                          "cssClassNames": [
                                            {
                                              "cssClassName": "PC_SUCCESS_MODAL_LOGO "
                                            }
                                          ]
                                        },
                                        "group": "Form",
                                        "updatedAt": "23-Aug-2021",
                                        "createdAt": "23-Aug-2021",
                                        "order": 0,
                                        "type": "20012",
                                        "version": "1.0.0",
                                        "isLatest": true,
                                        "projectType": "web",
                                        "component": {
                                          "content": "Image",
                                          "type": "20012"
                                        },
                                        "events": [],
                                        "path": "0-0-0-0-0"
                                      }
                                    ],
                                    "layoutProperties": {
                                      "xl": 12,
                                      "lg": 12,
                                      "md": 12,
                                      "sm": 12,
                                      "xs": 12
                                    }
                                  }
                                ],
                                "allowedContainers": [
                                  "10001",
                                  "20030",
                                  "noLayout",
                                  "20010",
                                  "widget"
                                ],
                                "attributes": {
                                  "gridProps": [],
                                  "label": "Header",
                                  "layoutProperties": {
                                    "gridLayout": {
                                      "//": "Use this class to style grid layout component.",
                                      "spacing": 0
                                    },
                                    "mainContainer": "gridLayout"
                                  },
                                  "layoutProps": {
                                    "direction": "row",
                                    "justifyContent": "flex-start",
                                    "alignItems": "flex-start"
                                  },
                                  "direction": "row",
                                  "name": "Grid layout"
                                },
                                "events": [],
                                "component": {
                                  "type": "10001",
                                  "content": "Grid layout"
                                },
                                "path": "0-0-0-0-0"
                              },
                              {
                                "type": "10001",
                                "name": "Grid layout",
                                "id": "IehYbx2gTm3f1lukdFtq2",
                                "gridProps": [
                                  {
                                    "type": "column",
                                    "id": "PHeFVKORtDfTZN4WXjyVe",
                                    "gridProps": [
                                      {
                                        "id": "gTs4-u3od8hjCzfVj2miZ",
                                        "status": "ACTIVE",
                                        "name": "Label",
                                        "attributes": {
                                          "variant": "body1",
                                          "name": "Label",
                                          "mandatory": false,
                                          "layoutProperties": {
                                            "label": {
                                              "//": "Use this class to style label component."
                                            },
                                            "mainContainer": "label",
                                            "xl": 12,
                                            "lg": 12,
                                            "md": 12,
                                            "sm": 12,
                                            "xs": 12
                                          },
                                          "label": "Amount transfered",
                                          "cssClassNames": [
                                            {
                                              "cssClassName": "PC_SUCCESS_TITLE "
                                            }
                                          ]
                                        },
                                        "icon": "FaFont",
                                        "group": "Form",
                                        "type": "20002",
                                        "updatedAt": "23-Aug-2021",
                                        "createdAt": "23-Aug-2021",
                                        "order": 15,
                                        "version": "1.0.0",
                                        "isLatest": true,
                                        "projectType": "web",
                                        "component": {
                                          "content": "Label",
                                          "type": "20002"
                                        },
                                        "events": [],
                                        "path": "0-0-0-0-0-0-1-0-0"
                                      },
                                      {
                                        "id": "Pl_2h8J-TK6YYt6oJpUQE",
                                        "status": "ACTIVE",
                                        "name": "Label",
                                        "attributes": {
                                          "variant": "body1",
                                          "name": "Label",
                                          "mandatory": false,
                                          "layoutProperties": {
                                            "label": {
                                              "//": "Use this class to style label component."
                                            },
                                            "mainContainer": "label",
                                            "xl": 12,
                                            "lg": 12,
                                            "md": 12,
                                            "sm": 12,
                                            "xs": 12
                                          },
                                          "label": "tbg_response.message",
                                          "cssClassNames": [
                                            {
                                              "cssClassName": "PC_SUCCESS_MODAL_BODY "
                                            }
                                          ],
                                          "searchInState": true,
                                          "storeType": 2
                                        },
                                        "icon": "FaFont",
                                        "group": "Form",
                                        "type": "20002",
                                        "updatedAt": "23-Aug-2021",
                                        "createdAt": "23-Aug-2021",
                                        "order": 15,
                                        "version": "1.0.0",
                                        "isLatest": true,
                                        "projectType": "web",
                                        "component": {
                                          "content": "Label",
                                          "type": "20002"
                                        },
                                        "events": [],
                                        "path": "0-0-0-0-0-0-1-0-1"
                                      }
                                    ],
                                    "layoutProperties": {
                                      "xl": 12,
                                      "lg": 12,
                                      "md": 12,
                                      "sm": 12,
                                      "xs": 12
                                    }
                                  }
                                ],
                                "allowedContainers": [
                                  "10001",
                                  "20030",
                                  "noLayout",
                                  "20010",
                                  "widget"
                                ],
                                "attributes": {
                                  "gridProps": [],
                                  "label": "Header",
                                  "layoutProperties": {
                                    "gridLayout": {
                                      "//": "Use this class to style grid layout component.",
                                      "padding": "5px",
                                      "spacing": 0
                                    },
                                    "mainContainer": "gridLayout"
                                  },
                                  "layoutProps": {
                                    "direction": "row",
                                    "justifyContent": "flex-start",
                                    "alignItems": "flex-start"
                                  },
                                  "direction": "row",
                                  "name": "Grid layout"
                                },
                                "events": [],
                                "component": {
                                  "type": "10001",
                                  "content": "Grid layout"
                                },
                                "path": "0-0-1"
                              },
                              {
                                "id": "-L2pyxpfFNfHBK-KmbwQY",
                                "status": "ACTIVE",
                                "attributes": {
                                  "label": "",
                                  "variant": "contained",
                                  "name": "Button",
                                  "label-locale-key": "",
                                  "fullWidth": true,
                                  "layoutProperties": {
                                    "button": {
                                      "//": "Use this class to style button component."
                                    },
                                    "iconButton": {
                                      "//": "Use this class to style icon button component.",
                                      "width": "20px",
                                      "height": "20px"
                                    },
                                    "inputProps": {
                                      "//": "Use this class to style button element."
                                    },
                                    "mainContainer": "button",
                                    "xl": 12,
                                    "lg": 12,
                                    "md": 12,
                                    "sm": 12,
                                    "xs": 12
                                  }
                                },
                                "name": "Button",
                                "icon": "FaBimobject",
                                "group": "Form",
                                "type": "20006",
                                "Documentation": "<div>components 12344</div>",
                                "updatedAt": "23-Aug-2021",
                                "createdAt": "23-Aug-2021",
                                "order": 1,
                                "version": "1.0.0",
                                "isLatest": true,
                                "projectType": "web",
                                "component": {
                                  "content": "Button",
                                  "type": "20006"
                                },
                                "events": [],
                                "path": "0-0-2"
                              },
                              {
                                "id": "2Eyx5zilQSqR_B8Oe0NtY",
                                "status": "ACTIVE",
                                "attributes": {
                                  "label": "Done",
                                  "variant": "contained",
                                  "name": "Button",
                                  "label-locale-key": "",
                                  "fullWidth": true,
                                  "layoutProperties": {
                                    "button": {
                                      "//": "Use this class to style button component."
                                    },
                                    "iconButton": {
                                      "//": "Use this class to style icon button component.",
                                      "width": "20px",
                                      "height": "20px"
                                    },
                                    "inputProps": {
                                      "//": "Use this class to style button element."
                                    },
                                    "mainContainer": "button",
                                    "xl": 12,
                                    "lg": 12,
                                    "md": 12,
                                    "sm": 12,
                                    "xs": 12
                                  },
                                  "cssClassNames": [
                                    {
                                      "cssClassName": "PC_SUCCESS_MODAL_BUTTON "
                                    }
                                  ]
                                },
                                "name": "Button",
                                "icon": "FaBimobject",
                                "group": "Form",
                                "type": "20006",
                                "Documentation": "<div>components 12344</div>",
                                "updatedAt": "23-Aug-2021",
                                "createdAt": "23-Aug-2021",
                                "order": 1,
                                "version": "1.0.0",
                                "isLatest": true,
                                "projectType": "web",
                                "component": {
                                  "content": "Button",
                                  "type": "20006"
                                },
                                "events": [
                                  {
                                    "triggerId": "WuhHxg90Z2anPz7DGsIrC",
                                    "triggerName": "Close Modal",
                                    "serviceType": "9",
                                    "attributes": {
                                      "content": "",
                                      "type": "",
                                      "modalId": "ozKeLAA5SQp3bjJ9kCQQg",
                                      "toastContentType": "custom"
                                    },
                                    "type": "2",
                                    "name": "On click",
                                    "commandType": "2"
                                  }
                                ],
                                "path": "0-0-0-0-0-0-3"
                              }
                            ],
                            "layoutProperties": {
                              "xl": 12,
                              "lg": 12,
                              "md": 12,
                              "sm": 12,
                              "xs": 12
                            }
                          }
                        ],
                        "layoutProperties": {
                          "lg": 12,
                          "md": 12,
                          "sm": 12,
                          "xs": 12
                        },
                        "dimensions": {
                          "rows": 1,
                          "columns": 1,
                          "colSize0xs": 12,
                          "colSize0sm": 12,
                          "colSize0md": 12,
                          "colSize0lg": 12,
                          "colSize0xl": 12
                        },
                        "readOnly": true
                      },
                      {
                        "id": "VLDCMUuBmIeSriIbeICjV",
                        "status": "ACTIVE",
                        "_id": "610134a1d1f5e860b1e8c751",
                        "name": "TBW_ERROR",
                        "icon": "FaGripHorizontal",
                        "attributes": {
                          "gridProps": [],
                          "label": "Header",
                          "layoutProperties": {
                            "gridLayout": {
                              "//": "Use this class to style grid layout component.",
                              "spacing": 0
                            },
                            "mainContainer": "gridLayout"
                          },
                          "layoutProps": {
                            "direction": "row",
                            "justifyContent": "flex-start",
                            "alignItems": "flex-start"
                          },
                          "direction": "row",
                          "name": "TBW_ERROR",
                          "hideCondition": {
                            "logic": {
                              "if": [
                                {
                                  "==": [
                                    {
                                      "var": "currentScreen.tbg_response.code"
                                    },
                                    1
                                  ]
                                },
                                true,
                                false
                              ]
                            }
                          },
                          "cssClassNames": [
                            { "cssClassName": "PC_SUCCESS_MAIN " }
                          ]
                        },
                        "group": "Layout",
                        "type": "10001",
                        "updatedAt": "23-Sep-2021",
                        "Documentation": "<div>\n<table style=\"border-collapse: collapse; width: 99.8899%;\" border=\"1\">\n<tbody>\n<tr>\n<td style=\"width: 48.4024%;\">1</td>\n<td style=\"width: 48.4024%;\">&nbsp;</td>\n</tr>\n<tr>\n<td style=\"width: 48.4024%;\">2</td>\n<td style=\"width: 48.4024%;\">&nbsp;</td>\n</tr>\n<tr>\n<td style=\"width: 48.4024%;\">43</td>\n<td style=\"width: 48.4024%;\">&nbsp;</td>\n</tr>\n<tr>\n<td style=\"width: 48.4024%;\">6</td>\n<td style=\"width: 48.4024%;\">&nbsp;</td>\n</tr>\n<tr>\n<td style=\"width: 48.4024%;\">7</td>\n<td style=\"width: 48.4024%;\">&nbsp;</td>\n</tr>\n</tbody>\n</table>\nWrite your Docu7mentationtestsdfasd</div>",
                        "createdAt": "24-Aug-2021",
                        "events": [],
                        "order": 1,
                        "version": "1.0.0",
                        "isLatest": true,
                        "projectType": "web",
                        "allowedContainers": [
                          "10001",
                          "20030",
                          "noLayout",
                          "20010",
                          "widget"
                        ],
                        "component": {
                          "content": "Grid layout",
                          "type": "10001"
                        },
                        "path": "0-0-0-0-1",
                        "gridProps": [
                          {
                            "type": "column",
                            "id": "sfl1Hcw2l7K0OJQsRNXTv",
                            "gridProps": [
                              {
                                "type": "10001",
                                "name": "Grid layout",
                                "id": "5oty8SnWJw1vPw0zdKAdc",
                                "gridProps": [
                                  {
                                    "type": "column",
                                    "id": "1bpSefezVSvzN-rSPNqbX",
                                    "gridProps": [
                                      {
                                        "id": "VhslGzP2bLK4OSOEUQKBk",
                                        "status": "ACTIVE",
                                        "name": "Image",
                                        "icon": "FaImage",
                                        "attributes": {
                                          "name": "Image",
                                          "contentType": false,
                                          "defaultImageAssetIdTemp": {
                                            "name": "dracaena-cinnabari.jpg",
                                            "id": "CNIz67fi824LHr0ae-pOV"
                                          },
                                          "layoutProperties": {
                                            "image": {
                                              "//": "Use this class to style image component."
                                            },
                                            "mainContainer": "image",
                                            "xl": 12,
                                            "lg": 12,
                                            "md": 12,
                                            "sm": 12,
                                            "xs": 12
                                          },
                                          "defaultImageAssetId": "CNIz67fi824LHr0ae-pOV",
                                          "imageAssetIdTemp": {
                                            "createdBy": "user",
                                            "_id": "659fb31c87797c28bc6eac71",
                                            "name": "confirmation_error.png",
                                            "type": "png",
                                            "projectId": "652fcbce09869c3c809b3097",
                                            "id": "wLqcxwJN4gnJ07TQn_5fo",
                                            "gitBranchName": "master",
                                            "folderType": "web",
                                            "platform": "web",
                                            "url": "652fcbce09869c3c809b3097/web/confirmation_error.png",
                                            "canvasUrl": "652fcbce09869c3c809b3097/web/confirmation_error.png",
                                            "createdAt": "2024-01-11T09:21:32.304Z",
                                            "updatedAt": "2024-01-11T09:21:32.304Z",
                                            "__v": 0,
                                            "uri": "652fcbce09869c3c809b3097/web/confirmation_error.png"
                                          },
                                          "imageAssetId": "wLqcxwJN4gnJ07TQn_5fo",
                                          "stateName": null,
                                          "storeType": null,
                                          "useFullLink": null,
                                          "cssClassNames": [
                                            {
                                              "cssClassName": "PC_SUCCESS_MODAL_LOGO "
                                            }
                                          ]
                                        },
                                        "group": "Form",
                                        "updatedAt": "23-Aug-2021",
                                        "createdAt": "23-Aug-2021",
                                        "order": 0,
                                        "type": "20012",
                                        "version": "1.0.0",
                                        "isLatest": true,
                                        "projectType": "web",
                                        "component": {
                                          "content": "Image",
                                          "type": "20012"
                                        },
                                        "events": [],
                                        "path": "1-0-0-0-0"
                                      }
                                    ],
                                    "layoutProperties": {
                                      "xl": 12,
                                      "lg": 12,
                                      "md": 12,
                                      "sm": 12,
                                      "xs": 12
                                    }
                                  }
                                ],
                                "allowedContainers": [
                                  "10001",
                                  "20030",
                                  "noLayout",
                                  "20010",
                                  "widget"
                                ],
                                "attributes": {
                                  "gridProps": [],
                                  "label": "Header",
                                  "layoutProperties": {
                                    "gridLayout": {
                                      "//": "Use this class to style grid layout component.",
                                      "spacing": 0
                                    },
                                    "mainContainer": "gridLayout"
                                  },
                                  "layoutProps": {
                                    "direction": "row",
                                    "justifyContent": "flex-start",
                                    "alignItems": "flex-start"
                                  },
                                  "direction": "row",
                                  "name": "Grid layout"
                                },
                                "events": [],
                                "component": {
                                  "type": "10001",
                                  "content": "Grid layout"
                                }
                              },
                              {
                                "type": "10001",
                                "name": "Grid layout",
                                "id": "fufcFVM8OLPv6wM9vHkvt",
                                "gridProps": [
                                  {
                                    "type": "column",
                                    "id": "KUFVvserp1e-Z8T2F9sfp",
                                    "gridProps": [
                                      {
                                        "id": "52Fl6idOgEq-IinyQbvbM",
                                        "status": "ACTIVE",
                                        "name": "Label",
                                        "attributes": {
                                          "variant": "body1",
                                          "name": "Label",
                                          "mandatory": false,
                                          "layoutProperties": {
                                            "label": {
                                              "//": "Use this class to style label component."
                                            },
                                            "mainContainer": "label",
                                            "xl": 12,
                                            "lg": 12,
                                            "md": 12,
                                            "sm": 12,
                                            "xs": 12
                                          },
                                          "label": "Transfer failed",
                                          "cssClassNames": [
                                            {
                                              "cssClassName": "PC_SUCCESS_TITLE "
                                            }
                                          ]
                                        },
                                        "icon": "FaFont",
                                        "group": "Form",
                                        "type": "20002",
                                        "updatedAt": "23-Aug-2021",
                                        "createdAt": "23-Aug-2021",
                                        "order": 15,
                                        "version": "1.0.0",
                                        "isLatest": true,
                                        "projectType": "web",
                                        "component": {
                                          "content": "Label",
                                          "type": "20002"
                                        },
                                        "events": [],
                                        "path": "0-0-0-0-1-0-1-0-0"
                                      },
                                      {
                                        "id": "vQHrZ9kwPECSWKLPqpwvP",
                                        "status": "ACTIVE",
                                        "name": "Label",
                                        "attributes": {
                                          "variant": "body1",
                                          "name": "Label",
                                          "mandatory": false,
                                          "layoutProperties": {
                                            "label": {
                                              "//": "Use this class to style label component."
                                            },
                                            "mainContainer": "label",
                                            "xl": 12,
                                            "lg": 12,
                                            "md": 12,
                                            "sm": 12,
                                            "xs": 12
                                          },
                                          "label": "tbg_response.message",
                                          "cssClassNames": [
                                            {
                                              "cssClassName": "PC_SUCCESS_MODAL_BODY "
                                            }
                                          ],
                                          "searchInState": true,
                                          "storeType": 2,
                                          "hideCondition": { "logic": false }
                                        },
                                        "icon": "FaFont",
                                        "group": "Form",
                                        "type": "20002",
                                        "updatedAt": "23-Aug-2021",
                                        "createdAt": "23-Aug-2021",
                                        "order": 15,
                                        "version": "1.0.0",
                                        "isLatest": true,
                                        "projectType": "web",
                                        "component": {
                                          "content": "Label",
                                          "type": "20002"
                                        },
                                        "events": [],
                                        "path": "0-0-0-0-1-0-1-0-1"
                                      }
                                    ],
                                    "layoutProperties": {
                                      "xl": 12,
                                      "lg": 12,
                                      "md": 12,
                                      "sm": 12,
                                      "xs": 12
                                    }
                                  }
                                ],
                                "allowedContainers": [
                                  "10001",
                                  "20030",
                                  "noLayout",
                                  "20010",
                                  "widget"
                                ],
                                "attributes": {
                                  "gridProps": [],
                                  "label": "Header",
                                  "layoutProperties": {
                                    "gridLayout": {
                                      "//": "Use this class to style grid layout component.",
                                      "spacing": 0
                                    },
                                    "mainContainer": "gridLayout"
                                  },
                                  "layoutProps": {
                                    "direction": "row",
                                    "justifyContent": "flex-start",
                                    "alignItems": "flex-start"
                                  },
                                  "direction": "row",
                                  "name": "Grid layout"
                                },
                                "events": [],
                                "component": {
                                  "type": "10001",
                                  "content": "Grid layout"
                                },
                                "path": "0-0-1-0-1"
                              },
                              {
                                "id": "kimGY2bmzx1EBWUG8Qrbq",
                                "status": "ACTIVE",
                                "attributes": {
                                  "label": "Cancel",
                                  "variant": "contained",
                                  "name": "Button",
                                  "label-locale-key": "",
                                  "fullWidth": true,
                                  "layoutProperties": {
                                    "button": {
                                      "//": "Use this class to style button component."
                                    },
                                    "iconButton": {
                                      "//": "Use this class to style icon button component.",
                                      "width": "20px",
                                      "height": "20px"
                                    },
                                    "inputProps": {
                                      "//": "Use this class to style button element."
                                    },
                                    "mainContainer": "button",
                                    "xl": 12,
                                    "lg": 12,
                                    "md": 12,
                                    "sm": 12,
                                    "xs": 12
                                  },
                                  "cssClassNames": [
                                    {
                                      "cssClassName": "PC_SUCCESS_MODAL_BUTTON "
                                    }
                                  ],
                                  "hideCondition": {
                                    "logic": {
                                      "if": [
                                        {
                                          "var": "currentScreen.pc_release_payment.content.reference"
                                        },
                                        true,
                                        false
                                      ]
                                    }
                                  }
                                },
                                "name": "Button",
                                "icon": "FaBimobject",
                                "group": "Form",
                                "type": "20006",
                                "Documentation": "<div>components 12344</div>",
                                "updatedAt": "23-Aug-2021",
                                "createdAt": "23-Aug-2021",
                                "order": 1,
                                "version": "1.0.0",
                                "isLatest": true,
                                "projectType": "web",
                                "component": {
                                  "content": "Button",
                                  "type": "20006"
                                },
                                "events": [
                                  {
                                    "triggerId": "WuhHxg90Z2anPz7DGsIrC",
                                    "triggerName": "Close Modal",
                                    "serviceType": "9",
                                    "attributes": {
                                      "content": "",
                                      "type": "",
                                      "modalId": "ozKeLAA5SQp3bjJ9kCQQg",
                                      "toastContentType": "custom"
                                    },
                                    "type": "2",
                                    "name": "On click",
                                    "commandType": "2"
                                  }
                                ],
                                "path": "0-0-0-0-1-0-2"
                              }
                            ],
                            "layoutProperties": {
                              "xl": 12,
                              "lg": 12,
                              "md": 12,
                              "sm": 12,
                              "xs": 12
                            }
                          }
                        ],
                        "layoutProperties": {
                          "lg": 12,
                          "md": 12,
                          "sm": 12,
                          "xs": 12
                        },
                        "dimensions": {
                          "rows": 1,
                          "columns": 1,
                          "colSize0xs": 12,
                          "colSize0sm": 12,
                          "colSize0md": 12,
                          "colSize0lg": 12,
                          "colSize0xl": 12,
                          "name": null
                        },
                        "readOnly": true
                      }
                    ],
                    "layoutProperties": {
                      "xl": 12,
                      "lg": 12,
                      "md": 12,
                      "sm": 12,
                      "xs": 12
                    }
                  }
                ],
                "layoutProperties": { "lg": 12, "md": 12, "sm": 12, "xs": 12 }
              }
            ],
            "layoutProperties": {
              "xl": 12,
              "lg": 12,
              "md": 12,
              "sm": 12,
              "xs": 12
            },
            "path": "0-0"
          }
        ],
        "layoutProperties": { "lg": 12, "md": 12, "sm": 12, "xs": 12 }
      }
    ],
    "events": [],
    "subType": "widget",
    "screenId": "hYVmHpX7q_9c5ft3KAZQ4",
    "projectId": "652fcbce09869c3c809b3097",
    "version": "1.0.0",
    "gitBranchName": "master",
    "_id": "hYVmHpX7q_9c5ft3KAZQ4",
    "createdBy": "talha",
    "updatedAt": "3/29/2024",
    "createdAt": "3/29/2024",
    "updatedTimestamp": "0000-00-00T00:00:00+00:00"
  },
  {
    "id": "cvSg1Z5gK6PqGfzaQpRbe",
    "name": "Grid layout",
    "type": "10001",
    "attributes": {
      "gridProps": [
        {
          "componentId": "aiZMz2PZZ_zMx_ea7xbqf",
          "componentType": "10001",
          "id": "aiZMz2PZZ_zMx_ea7xbqf",
          "position": {
            "i": "aiZMz2PZZ_zMx_ea7xbqf",
            "x": null,
            "y": null,
            "w": null,
            "h": null
          },
          "layoutProperties": {
            "xl": 12,
            "lg": 12,
            "md": 12,
            "sm": 12,
            "xs": 12
          }
        }
      ],
      "label": "Header",
      "layoutProperties": {
        "gridLayout": {
          "//": "Use this class to style grid layout component.",
          "spacing": 0
        },
        "mainContainer": "gridLayout",
        "skeleton": {
          "//": "Use this class to style skeleton loading component."
        }
      },
      "layoutProps": {
        "direction": "row",
        "justifyContent": "flex-start",
        "alignItems": "flex-start"
      },
      "direction": "row",
      "name": "TBG_RESPONSE"
    },
    "layout": null,
    "events": [],
    "subType": "component",
    "screenId": "hYVmHpX7q_9c5ft3KAZQ4",
    "projectId": "652fcbce09869c3c809b3097",
    "version": "1.0.0",
    "gitBranchName": "master",
    "updatedTimestamp": "0000-00-00T00:00:00+00:00"
  },
  {
    "id": "aiZMz2PZZ_zMx_ea7xbqf",
    "name": "Grid layout",
    "type": "10001",
    "attributes": {
      "gridProps": [
        {
          "componentId": "iO0q4XZ3NIAgnPkpQbUYO",
          "componentType": "10001",
          "id": "iO0q4XZ3NIAgnPkpQbUYO",
          "position": {
            "i": "iO0q4XZ3NIAgnPkpQbUYO",
            "x": null,
            "y": null,
            "w": null,
            "h": null
          },
          "layoutProperties": {
            "xl": 12,
            "lg": 12,
            "md": 12,
            "sm": 12,
            "xs": 12
          }
        },
        {
          "componentId": "VLDCMUuBmIeSriIbeICjV",
          "componentType": "10001",
          "id": "VLDCMUuBmIeSriIbeICjV",
          "position": {
            "i": "VLDCMUuBmIeSriIbeICjV",
            "x": null,
            "y": null,
            "w": null,
            "h": null
          },
          "layoutProperties": {
            "xl": 12,
            "lg": 12,
            "md": 12,
            "sm": 12,
            "xs": 12
          }
        }
      ],
      "label": "Header",
      "layoutProperties": {
        "gridLayout": {
          "//": "Use this class to style grid layout component.",
          "spacing": 0
        },
        "mainContainer": "gridLayout"
      },
      "layoutProps": {
        "direction": "row",
        "justifyContent": "flex-start",
        "alignItems": "flex-start"
      },
      "direction": "row",
      "name": "Grid layout"
    },
    "layout": null,
    "events": [],
    "subType": "component",
    "screenId": "hYVmHpX7q_9c5ft3KAZQ4",
    "projectId": "652fcbce09869c3c809b3097",
    "version": "1.0.0",
    "gitBranchName": "master",
    "updatedTimestamp": "0000-00-00T00:00:00+00:00"
  },
  {
    "id": "iO0q4XZ3NIAgnPkpQbUYO",
    "name": "TBW_SUCCESS_2",
    "type": "10001",
    "attributes": {
      "gridProps": [
        {
          "componentId": "wtf2SHMxCSObwZ45GCR1r",
          "componentType": "10001",
          "id": "wtf2SHMxCSObwZ45GCR1r",
          "position": {
            "i": "wtf2SHMxCSObwZ45GCR1r",
            "x": null,
            "y": null,
            "w": null,
            "h": null
          },
          "layoutProperties": {
            "xl": 12,
            "lg": 12,
            "md": 12,
            "sm": 12,
            "xs": 12
          }
        },
        {
          "componentId": "IehYbx2gTm3f1lukdFtq2",
          "componentType": "10001",
          "id": "IehYbx2gTm3f1lukdFtq2",
          "position": {
            "i": "IehYbx2gTm3f1lukdFtq2",
            "x": null,
            "y": null,
            "w": null,
            "h": null
          },
          "layoutProperties": {
            "xl": 12,
            "lg": 12,
            "md": 12,
            "sm": 12,
            "xs": 12
          }
        },
        {
          "layoutProperties": {
            "xl": 12,
            "lg": 12,
            "md": 12,
            "sm": 12,
            "xs": 12
          },
          "componentId": "-L2pyxpfFNfHBK-KmbwQY",
          "componentType": "20006",
          "order": 1
        },
        {
          "layoutProperties": {
            "xl": 12,
            "lg": 12,
            "md": 12,
            "sm": 12,
            "xs": 12
          },
          "componentId": "2Eyx5zilQSqR_B8Oe0NtY",
          "componentType": "20006",
          "order": 1
        }
      ],
      "label": "Header",
      "layoutProperties": {
        "gridLayout": {
          "//": "Use this class to style grid layout component.",
          "spacing": 0
        },
        "mainContainer": "gridLayout"
      },
      "layoutProps": {
        "direction": "row",
        "justifyContent": "flex-start",
        "alignItems": "flex-start"
      },
      "direction": "row",
      "name": "TBW_SUCCESS_2",
      "cssClassNames": [{ "cssClassName": "PC_SUCCESS_MAIN " }],
      "hideCondition": {
        "logic": {
          "if": [
            { "==": [{ "var": "currentScreen.tbg_response.code" }, 1] },
            false,
            true
          ]
        }
      }
    },
    "layout": null,
    "events": [],
    "subType": "component",
    "screenId": "hYVmHpX7q_9c5ft3KAZQ4",
    "projectId": "652fcbce09869c3c809b3097",
    "version": "1.0.0",
    "gitBranchName": "master",
    "updatedTimestamp": "0000-00-00T00:00:00+00:00"
  },
  {
    "id": "wtf2SHMxCSObwZ45GCR1r",
    "name": "Grid layout",
    "type": "10001",
    "attributes": {
      "gridProps": [
        {
          "layoutProperties": {
            "xl": 12,
            "lg": 12,
            "md": 12,
            "sm": 12,
            "xs": 12
          },
          "componentId": "b8HUsIht0q-HEFKi0g4Xh",
          "componentType": "20012",
          "order": 1
        }
      ],
      "label": "Header",
      "layoutProperties": {
        "gridLayout": {
          "//": "Use this class to style grid layout component.",
          "spacing": 0
        },
        "mainContainer": "gridLayout"
      },
      "layoutProps": {
        "direction": "row",
        "justifyContent": "flex-start",
        "alignItems": "flex-start"
      },
      "direction": "row",
      "name": "Grid layout"
    },
    "layout": null,
    "events": [],
    "subType": "component",
    "screenId": "hYVmHpX7q_9c5ft3KAZQ4",
    "projectId": "652fcbce09869c3c809b3097",
    "version": "1.0.0",
    "gitBranchName": "master",
    "updatedTimestamp": "0000-00-00T00:00:00+00:00"
  },
  {
    "id": "b8HUsIht0q-HEFKi0g4Xh",
    "status": "ACTIVE",
    "name": "Image",
    "icon": "FaImage",
    "attributes": {
      "name": "Image",
      "contentType": false,
      "defaultImageAssetIdTemp": {
        "name": "dracaena-cinnabari.jpg",
        "id": "CNIz67fi824LHr0ae-pOV"
      },
      "layoutProperties": {
        "image": { "//": "Use this class to style image component." },
        "mainContainer": "image",
        "xl": 12,
        "lg": 12,
        "md": 12,
        "sm": 12,
        "xs": 12
      },
      "defaultImageAssetId": "CNIz67fi824LHr0ae-pOV",
      "imageAssetIdTemp": {
        "createdBy": "user",
        "_id": "659fb17887797c28bc6eabe0",
        "name": "confirmation_success.png",
        "type": "png",
        "projectId": "652fcbce09869c3c809b3097",
        "id": "WV75Y8fs8dlTXUpY7VD4D",
        "gitBranchName": "master",
        "folderType": "web",
        "platform": "web",
        "url": "652fcbce09869c3c809b3097/web/confirmation_success.png",
        "canvasUrl": "652fcbce09869c3c809b3097/web/confirmation_success.png",
        "createdAt": "2024-01-11T09:14:32.911Z",
        "updatedAt": "2024-01-11T09:14:32.911Z",
        "__v": 0,
        "uri": "652fcbce09869c3c809b3097/web/confirmation_success.png"
      },
      "imageAssetId": "WV75Y8fs8dlTXUpY7VD4D",
      "stateName": null,
      "storeType": null,
      "useFullLink": null,
      "cssClassNames": [{ "cssClassName": "PC_SUCCESS_MODAL_LOGO " }]
    },
    "group": "Form",
    "updatedAt": "23-Aug-2021",
    "createdAt": "23-Aug-2021",
    "order": 0,
    "type": "20012",
    "version": "1.0.0",
    "isLatest": true,
    "projectType": "web",
    "component": { "content": "Image", "type": "20012" },
    "events": [],
    "path": "0-0-0-0-0",
    "screenId": "hYVmHpX7q_9c5ft3KAZQ4",
    "subType": "component",
    "projectId": "652fcbce09869c3c809b3097",
    "gitBranchName": "master",
    "updatedTimestamp": "0000-00-00T00:00:00+00:00"
  },
  {
    "id": "IehYbx2gTm3f1lukdFtq2",
    "name": "Grid layout",
    "type": "10001",
    "attributes": {
      "gridProps": [
        {
          "layoutProperties": {
            "xl": 12,
            "lg": 12,
            "md": 12,
            "sm": 12,
            "xs": 12
          },
          "componentId": "gTs4-u3od8hjCzfVj2miZ",
          "componentType": "20002",
          "order": 1
        },
        {
          "layoutProperties": {
            "xl": 12,
            "lg": 12,
            "md": 12,
            "sm": 12,
            "xs": 12
          },
          "componentId": "Pl_2h8J-TK6YYt6oJpUQE",
          "componentType": "20002",
          "order": 1
        }
      ],
      "label": "Header",
      "layoutProperties": {
        "gridLayout": {
          "//": "Use this class to style grid layout component.",
          "padding": "5px",
          "spacing": 0
        },
        "mainContainer": "gridLayout"
      },
      "layoutProps": {
        "direction": "row",
        "justifyContent": "flex-start",
        "alignItems": "flex-start"
      },
      "direction": "row",
      "name": "Grid layout"
    },
    "layout": null,
    "events": [],
    "subType": "component",
    "screenId": "hYVmHpX7q_9c5ft3KAZQ4",
    "projectId": "652fcbce09869c3c809b3097",
    "version": "1.0.0",
    "gitBranchName": "master",
    "updatedTimestamp": "0000-00-00T00:00:00+00:00"
  },
  {
    "id": "gTs4-u3od8hjCzfVj2miZ",
    "status": "ACTIVE",
    "name": "Label",
    "attributes": {
      "variant": "body1",
      "name": "Label",
      "mandatory": false,
      "layoutProperties": {
        "label": { "//": "Use this class to style label component." },
        "mainContainer": "label",
        "xl": 12,
        "lg": 12,
        "md": 12,
        "sm": 12,
        "xs": 12
      },
      "label": "Amount transfered",
      "cssClassNames": [{ "cssClassName": "PC_SUCCESS_TITLE " }]
    },
    "icon": "FaFont",
    "group": "Form",
    "type": "20002",
    "updatedAt": "23-Aug-2021",
    "createdAt": "23-Aug-2021",
    "order": 15,
    "version": "1.0.0",
    "isLatest": true,
    "projectType": "web",
    "component": { "content": "Label", "type": "20002" },
    "events": [],
    "path": "0-0-0-0-0-0-1-0-0",
    "screenId": "hYVmHpX7q_9c5ft3KAZQ4",
    "subType": "component",
    "projectId": "652fcbce09869c3c809b3097",
    "gitBranchName": "master",
    "updatedTimestamp": "0000-00-00T00:00:00+00:00"
  },
  {
    "id": "Pl_2h8J-TK6YYt6oJpUQE",
    "status": "ACTIVE",
    "name": "Label",
    "attributes": {
      "variant": "body1",
      "name": "Label",
      "mandatory": false,
      "layoutProperties": {
        "label": { "//": "Use this class to style label component." },
        "mainContainer": "label",
        "xl": 12,
        "lg": 12,
        "md": 12,
        "sm": 12,
        "xs": 12
      },
      "label": "tbg_response.message",
      "cssClassNames": [{ "cssClassName": "PC_SUCCESS_MODAL_BODY " }],
      "searchInState": true,
      "storeType": 2
    },
    "icon": "FaFont",
    "group": "Form",
    "type": "20002",
    "updatedAt": "23-Aug-2021",
    "createdAt": "23-Aug-2021",
    "order": 15,
    "version": "1.0.0",
    "isLatest": true,
    "projectType": "web",
    "component": { "content": "Label", "type": "20002" },
    "events": [],
    "path": "0-0-0-0-0-0-1-0-1",
    "screenId": "hYVmHpX7q_9c5ft3KAZQ4",
    "subType": "component",
    "projectId": "652fcbce09869c3c809b3097",
    "gitBranchName": "master",
    "updatedTimestamp": "0000-00-00T00:00:00+00:00"
  },
  {
    "id": "-L2pyxpfFNfHBK-KmbwQY",
    "status": "ACTIVE",
    "attributes": {
      "label": "",
      "variant": "contained",
      "name": "Button",
      "label-locale-key": "",
      "fullWidth": true,
      "layoutProperties": {
        "button": { "//": "Use this class to style button component." },
        "iconButton": {
          "//": "Use this class to style icon button component.",
          "width": "20px",
          "height": "20px"
        },
        "inputProps": { "//": "Use this class to style button element." },
        "mainContainer": "button",
        "xl": 12,
        "lg": 12,
        "md": 12,
        "sm": 12,
        "xs": 12
      }
    },
    "name": "Button",
    "icon": "FaBimobject",
    "group": "Form",
    "type": "20006",
    "Documentation": "<div>components 12344</div>",
    "updatedAt": "23-Aug-2021",
    "createdAt": "23-Aug-2021",
    "order": 1,
    "version": "1.0.0",
    "isLatest": true,
    "projectType": "web",
    "component": { "content": "Button", "type": "20006" },
    "events": [],
    "path": "0-0-2",
    "screenId": "hYVmHpX7q_9c5ft3KAZQ4",
    "subType": "component",
    "projectId": "652fcbce09869c3c809b3097",
    "gitBranchName": "master",
    "updatedTimestamp": "0000-00-00T00:00:00+00:00"
  },
  {
    "id": "2Eyx5zilQSqR_B8Oe0NtY",
    "status": "ACTIVE",
    "attributes": {
      "label": "Done",
      "variant": "contained",
      "name": "Button",
      "label-locale-key": "",
      "fullWidth": true,
      "layoutProperties": {
        "button": { "//": "Use this class to style button component." },
        "iconButton": {
          "//": "Use this class to style icon button component.",
          "width": "20px",
          "height": "20px"
        },
        "inputProps": { "//": "Use this class to style button element." },
        "mainContainer": "button",
        "xl": 12,
        "lg": 12,
        "md": 12,
        "sm": 12,
        "xs": 12
      },
      "cssClassNames": [{ "cssClassName": "PC_SUCCESS_MODAL_BUTTON " }]
    },
    "name": "Button",
    "icon": "FaBimobject",
    "group": "Form",
    "type": "20006",
    "Documentation": "<div>components 12344</div>",
    "updatedAt": "23-Aug-2021",
    "createdAt": "23-Aug-2021",
    "order": 1,
    "version": "1.0.0",
    "isLatest": true,
    "projectType": "web",
    "component": { "content": "Button", "type": "20006" },
    "events": [
      {
        "triggerId": "WuhHxg90Z2anPz7DGsIrC",
        "triggerName": "Close Modal",
        "name": "On click",
        "type": "2",
        "serviceType": "9"
      }
    ],
    "path": "0-0-0-0-0-0-3",
    "screenId": "hYVmHpX7q_9c5ft3KAZQ4",
    "subType": "component",
    "projectId": "652fcbce09869c3c809b3097",
    "gitBranchName": "master",
    "updatedTimestamp": "0000-00-00T00:00:00+00:00"
  },
  {
    "id": "VLDCMUuBmIeSriIbeICjV",
    "name": "TBW_ERROR",
    "type": "10001",
    "attributes": {
      "gridProps": [
        {
          "componentId": "5oty8SnWJw1vPw0zdKAdc",
          "componentType": "10001",
          "id": "5oty8SnWJw1vPw0zdKAdc",
          "position": {
            "i": "5oty8SnWJw1vPw0zdKAdc",
            "x": null,
            "y": null,
            "w": null,
            "h": null
          },
          "layoutProperties": {
            "xl": 12,
            "lg": 12,
            "md": 12,
            "sm": 12,
            "xs": 12
          }
        },
        {
          "componentId": "fufcFVM8OLPv6wM9vHkvt",
          "componentType": "10001",
          "id": "fufcFVM8OLPv6wM9vHkvt",
          "position": {
            "i": "fufcFVM8OLPv6wM9vHkvt",
            "x": null,
            "y": null,
            "w": null,
            "h": null
          },
          "layoutProperties": {
            "xl": 12,
            "lg": 12,
            "md": 12,
            "sm": 12,
            "xs": 12
          }
        },
        {
          "layoutProperties": {
            "xl": 12,
            "lg": 12,
            "md": 12,
            "sm": 12,
            "xs": 12
          },
          "componentId": "kimGY2bmzx1EBWUG8Qrbq",
          "componentType": "20006",
          "order": 1
        }
      ],
      "label": "Header",
      "layoutProperties": {
        "gridLayout": {
          "//": "Use this class to style grid layout component.",
          "spacing": 0
        },
        "mainContainer": "gridLayout"
      },
      "layoutProps": {
        "direction": "row",
        "justifyContent": "flex-start",
        "alignItems": "flex-start"
      },
      "direction": "row",
      "name": "TBW_ERROR",
      "hideCondition": {
        "logic": {
          "if": [
            { "==": [{ "var": "currentScreen.tbg_response.code" }, 1] },
            true,
            false
          ]
        }
      },
      "cssClassNames": [{ "cssClassName": "PC_SUCCESS_MAIN " }]
    },
    "layout": null,
    "events": [],
    "subType": "component",
    "screenId": "hYVmHpX7q_9c5ft3KAZQ4",
    "projectId": "652fcbce09869c3c809b3097",
    "version": "1.0.0",
    "gitBranchName": "master",
    "updatedTimestamp": "0000-00-00T00:00:00+00:00"
  },
  {
    "id": "5oty8SnWJw1vPw0zdKAdc",
    "name": "Grid layout",
    "type": "10001",
    "attributes": {
      "gridProps": [
        {
          "layoutProperties": {
            "xl": 12,
            "lg": 12,
            "md": 12,
            "sm": 12,
            "xs": 12
          },
          "componentId": "VhslGzP2bLK4OSOEUQKBk",
          "componentType": "20012",
          "order": 1
        }
      ],
      "label": "Header",
      "layoutProperties": {
        "gridLayout": {
          "//": "Use this class to style grid layout component.",
          "spacing": 0
        },
        "mainContainer": "gridLayout"
      },
      "layoutProps": {
        "direction": "row",
        "justifyContent": "flex-start",
        "alignItems": "flex-start"
      },
      "direction": "row",
      "name": "Grid layout"
    },
    "layout": null,
    "events": [],
    "subType": "component",
    "screenId": "hYVmHpX7q_9c5ft3KAZQ4",
    "projectId": "652fcbce09869c3c809b3097",
    "version": "1.0.0",
    "gitBranchName": "master",
    "updatedTimestamp": "0000-00-00T00:00:00+00:00"
  },
  {
    "id": "VhslGzP2bLK4OSOEUQKBk",
    "status": "ACTIVE",
    "name": "Image",
    "icon": "FaImage",
    "attributes": {
      "name": "Image",
      "contentType": false,
      "defaultImageAssetIdTemp": {
        "name": "dracaena-cinnabari.jpg",
        "id": "CNIz67fi824LHr0ae-pOV"
      },
      "layoutProperties": {
        "image": { "//": "Use this class to style image component." },
        "mainContainer": "image",
        "xl": 12,
        "lg": 12,
        "md": 12,
        "sm": 12,
        "xs": 12
      },
      "defaultImageAssetId": "CNIz67fi824LHr0ae-pOV",
      "imageAssetIdTemp": {
        "createdBy": "user",
        "_id": "659fb31c87797c28bc6eac71",
        "name": "confirmation_error.png",
        "type": "png",
        "projectId": "652fcbce09869c3c809b3097",
        "id": "wLqcxwJN4gnJ07TQn_5fo",
        "gitBranchName": "master",
        "folderType": "web",
        "platform": "web",
        "url": "652fcbce09869c3c809b3097/web/confirmation_error.png",
        "canvasUrl": "652fcbce09869c3c809b3097/web/confirmation_error.png",
        "createdAt": "2024-01-11T09:21:32.304Z",
        "updatedAt": "2024-01-11T09:21:32.304Z",
        "__v": 0,
        "uri": "652fcbce09869c3c809b3097/web/confirmation_error.png"
      },
      "imageAssetId": "wLqcxwJN4gnJ07TQn_5fo",
      "stateName": null,
      "storeType": null,
      "useFullLink": null,
      "cssClassNames": [{ "cssClassName": "PC_SUCCESS_MODAL_LOGO " }]
    },
    "group": "Form",
    "updatedAt": "23-Aug-2021",
    "createdAt": "23-Aug-2021",
    "order": 0,
    "type": "20012",
    "version": "1.0.0",
    "isLatest": true,
    "projectType": "web",
    "component": { "content": "Image", "type": "20012" },
    "events": [],
    "path": "1-0-0-0-0",
    "screenId": "hYVmHpX7q_9c5ft3KAZQ4",
    "subType": "component",
    "projectId": "652fcbce09869c3c809b3097",
    "gitBranchName": "master",
    "updatedTimestamp": "0000-00-00T00:00:00+00:00"
  },
  {
    "id": "fufcFVM8OLPv6wM9vHkvt",
    "name": "Grid layout",
    "type": "10001",
    "attributes": {
      "gridProps": [
        {
          "layoutProperties": {
            "xl": 12,
            "lg": 12,
            "md": 12,
            "sm": 12,
            "xs": 12
          },
          "componentId": "52Fl6idOgEq-IinyQbvbM",
          "componentType": "20002",
          "order": 1
        },
        {
          "layoutProperties": {
            "xl": 12,
            "lg": 12,
            "md": 12,
            "sm": 12,
            "xs": 12
          },
          "componentId": "vQHrZ9kwPECSWKLPqpwvP",
          "componentType": "20002",
          "order": 1
        }
      ],
      "label": "Header",
      "layoutProperties": {
        "gridLayout": {
          "//": "Use this class to style grid layout component.",
          "spacing": 0
        },
        "mainContainer": "gridLayout"
      },
      "layoutProps": {
        "direction": "row",
        "justifyContent": "flex-start",
        "alignItems": "flex-start"
      },
      "direction": "row",
      "name": "Grid layout"
    },
    "layout": null,
    "events": [],
    "subType": "component",
    "screenId": "hYVmHpX7q_9c5ft3KAZQ4",
    "projectId": "652fcbce09869c3c809b3097",
    "version": "1.0.0",
    "gitBranchName": "master",
    "updatedTimestamp": "0000-00-00T00:00:00+00:00"
  },
  {
    "id": "52Fl6idOgEq-IinyQbvbM",
    "status": "ACTIVE",
    "name": "Label",
    "attributes": {
      "variant": "body1",
      "name": "Label",
      "mandatory": false,
      "layoutProperties": {
        "label": { "//": "Use this class to style label component." },
        "mainContainer": "label",
        "xl": 12,
        "lg": 12,
        "md": 12,
        "sm": 12,
        "xs": 12
      },
      "label": "Transfer failed",
      "cssClassNames": [{ "cssClassName": "PC_SUCCESS_TITLE " }]
    },
    "icon": "FaFont",
    "group": "Form",
    "type": "20002",
    "updatedAt": "23-Aug-2021",
    "createdAt": "23-Aug-2021",
    "order": 15,
    "version": "1.0.0",
    "isLatest": true,
    "projectType": "web",
    "component": { "content": "Label", "type": "20002" },
    "events": [],
    "path": "0-0-0-0-1-0-1-0-0",
    "screenId": "hYVmHpX7q_9c5ft3KAZQ4",
    "subType": "component",
    "projectId": "652fcbce09869c3c809b3097",
    "gitBranchName": "master",
    "updatedTimestamp": "0000-00-00T00:00:00+00:00"
  },
  {
    "id": "vQHrZ9kwPECSWKLPqpwvP",
    "status": "ACTIVE",
    "name": "Label",
    "attributes": {
      "variant": "body1",
      "name": "Label",
      "mandatory": false,
      "layoutProperties": {
        "label": { "//": "Use this class to style label component." },
        "mainContainer": "label",
        "xl": 12,
        "lg": 12,
        "md": 12,
        "sm": 12,
        "xs": 12
      },
      "label": "tbg_response.message",
      "cssClassNames": [{ "cssClassName": "PC_SUCCESS_MODAL_BODY " }],
      "searchInState": true,
      "storeType": 2,
      "hideCondition": { "logic": false }
    },
    "icon": "FaFont",
    "group": "Form",
    "type": "20002",
    "updatedAt": "23-Aug-2021",
    "createdAt": "23-Aug-2021",
    "order": 15,
    "version": "1.0.0",
    "isLatest": true,
    "projectType": "web",
    "component": { "content": "Label", "type": "20002" },
    "events": [],
    "path": "0-0-0-0-1-0-1-0-1",
    "screenId": "hYVmHpX7q_9c5ft3KAZQ4",
    "subType": "component",
    "projectId": "652fcbce09869c3c809b3097",
    "gitBranchName": "master",
    "updatedTimestamp": "0000-00-00T00:00:00+00:00"
  },
  {
    "id": "kimGY2bmzx1EBWUG8Qrbq",
    "status": "ACTIVE",
    "attributes": {
      "label": "Cancel",
      "variant": "contained",
      "name": "Button",
      "label-locale-key": "",
      "fullWidth": true,
      "layoutProperties": {
        "button": { "//": "Use this class to style button component." },
        "iconButton": {
          "//": "Use this class to style icon button component.",
          "width": "20px",
          "height": "20px"
        },
        "inputProps": { "//": "Use this class to style button element." },
        "mainContainer": "button",
        "xl": 12,
        "lg": 12,
        "md": 12,
        "sm": 12,
        "xs": 12
      },
      "cssClassNames": [{ "cssClassName": "PC_SUCCESS_MODAL_BUTTON " }],
      "hideCondition": {
        "logic": {
          "if": [
            { "var": "currentScreen.pc_release_payment.content.reference" },
            true,
            false
          ]
        }
      }
    },
    "name": "Button",
    "icon": "FaBimobject",
    "group": "Form",
    "type": "20006",
    "Documentation": "<div>components 12344</div>",
    "updatedAt": "23-Aug-2021",
    "createdAt": "23-Aug-2021",
    "order": 1,
    "version": "1.0.0",
    "isLatest": true,
    "projectType": "web",
    "component": { "content": "Button", "type": "20006" },
    "events": [
      {
        "triggerId": "WuhHxg90Z2anPz7DGsIrC",
        "triggerName": "Close Modal",
        "name": "On click",
        "type": "2",
        "serviceType": "9"
      }
    ],
    "path": "0-0-0-0-1-0-2",
    "screenId": "hYVmHpX7q_9c5ft3KAZQ4",
    "subType": "component",
    "projectId": "652fcbce09869c3c809b3097",
    "gitBranchName": "master",
    "updatedTimestamp": "0000-00-00T00:00:00+00:00"
  }
]
